[
	{
		"ath": 4878.26,
		"ath_change_percentage": -63.12655,
		"ath_date": "2021-11-10T14:24:19.604Z",
		"atl": 0.432979,
		"atl_change_percentage": 415343.5497,
		"atl_date": "2015-10-20T00:00:00.000Z",
		"circulating_supply": 120448797.976576,
		"current_price": 1799.63,
		"fully_diluted_valuation": 216804024631,
		"high_24h": 1825.53,
		"id": "ethereum",
		"image": "https://assets.coingecko.com/coins/images/279/large/ethereum.png?1595348880",
		"last_updated": "2023-03-30T09:54:01.802Z",
		"low_24h": 1778.89,
		"market_cap": 216804024631,
		"market_cap_change_24h": -2135455205.547058,
		"market_cap_change_percentage_24h": -0.97536,
		"market_cap_rank": 2,
		"max_supply": null,
		"name": "Ethereum",
		"price_change_24h": -17.185620462205634,
		"price_change_percentage_24h": -0.94592,
		"roi": {
			"currency": "btc",
			"percentage": 8318.366497748304,
			"times": 83.18366497748305
		},
		"symbol": "eth",
		"total_supply": 120448797.976576,
		"total_volume": 10878994947
	},
	{
		"ath": 1.32,
		"ath_change_percentage": -24.38555,
		"ath_date": "2018-07-24T00:00:00.000Z",
		"atl": 0.572521,
		"atl_change_percentage": 74.74489,
		"atl_date": "2015-03-02T00:00:00.000Z",
		"circulating_supply": 79640898253.3991,
		"current_price": 1.001,
		"fully_diluted_valuation": 79721764765,
		"high_24h": 1.007,
		"id": "tether",
		"image": "https://assets.coingecko.com/coins/images/325/large/Tether.png?1668148663",
		"last_updated": "2023-03-30T09:50:01.462Z",
		"low_24h": 0.991465,
		"market_cap": 79721764765,
		"market_cap_change_24h": 205684280,
		"market_cap_change_percentage_24h": 0.25867,
		"market_cap_rank": 3,
		"max_supply": null,
		"name": "Tether",
		"price_change_24h": 0.00096463,
		"price_change_percentage_24h": 0.09646,
		"roi": null,
		"symbol": "usdt",
		"total_supply": 79640898253.3991,
		"total_volume": 34388074235
	},
	{
		"ath": 686.31,
		"ath_change_percentage": -54.07877,
		"ath_date": "2021-05-10T07:24:17.097Z",
		"atl": 0.0398177,
		"atl_change_percentage": 791408.45285,
		"atl_date": "2017-10-19T00:00:00.000Z",
		"circulating_supply": 157895234,
		"current_price": 315.48,
		"fully_diluted_valuation": 63139839653,
		"high_24h": 318.4,
		"id": "binancecoin",
		"image": "https://assets.coingecko.com/coins/images/825/large/bnb-icon2_2x.png?1644979850",
		"last_updated": "2023-03-30T09:53:57.511Z",
		"low_24h": 311.06,
		"market_cap": 49847398784,
		"market_cap_change_24h": -377660049.9910965,
		"market_cap_change_percentage_24h": -0.75194,
		"market_cap_rank": 4,
		"max_supply": 200000000,
		"name": "BNB",
		"price_change_24h": -2.495065098480552,
		"price_change_percentage_24h": -0.78468,
		"roi": null,
		"symbol": "bnb",
		"total_supply": 157900174,
		"total_volume": 537591887
	},
	{
		"ath": 1.17,
		"ath_change_percentage": -14.72302,
		"ath_date": "2019-05-08T00:40:28.300Z",
		"atl": 0.877647,
		"atl_change_percentage": 13.94658,
		"atl_date": "2023-03-11T08:02:13.981Z",
		"circulating_supply": 33265435063.0433,
		"current_price": 1.001,
		"fully_diluted_valuation": 33283337353,
		"high_24h": 1.005,
		"id": "usd-coin",
		"image": "https://assets.coingecko.com/coins/images/6319/large/USD_Coin_icon.png?1547042389",
		"last_updated": "2023-03-30T09:53:56.138Z",
		"low_24h": 0.995565,
		"market_cap": 33288360214,
		"market_cap_change_24h": -7056273.613868713,
		"market_cap_change_percentage_24h": -0.02119,
		"market_cap_rank": 5,
		"max_supply": null,
		"name": "USD Coin",
		"price_change_24h": 0.00021813,
		"price_change_percentage_24h": 0.0218,
		"roi": null,
		"symbol": "usdc",
		"total_supply": 33260415661.0433,
		"total_volume": 4764573350
	},
	{
		"ath": 4829.57,
		"ath_change_percentage": -62.8616,
		"ath_date": "2021-11-10T14:40:47.256Z",
		"atl": 482.9,
		"atl_change_percentage": 271.43079,
		"atl_date": "2020-12-22T04:08:21.854Z",
		"circulating_supply": 5882798.17555046,
		"current_price": 1796.11,
		"fully_diluted_valuation": 10567386483,
		"high_24h": 1820.27,
		"id": "staked-ether",
		"image": "https://assets.coingecko.com/coins/images/13442/large/steth_logo.png?1608607546",
		"last_updated": "2023-03-30T09:53:52.818Z",
		"low_24h": 1774.59,
		"market_cap": 10567212533,
		"market_cap_change_24h": 7766793,
		"market_cap_change_percentage_24h": 0.07355,
		"market_cap_rank": 8,
		"max_supply": 5882895.01382952,
		"name": "Lido Staked Ether",
		"price_change_24h": 5.11,
		"price_change_percentage_24h": 0.28519,
		"roi": null,
		"symbol": "steth",
		"total_supply": 5882895.01382952,
		"total_volume": 11205933
	},
	{
		"ath": 2.92,
		"ath_change_percentage": -61.94676,
		"ath_date": "2021-12-27T02:08:34.307Z",
		"atl": 0.00314376,
		"atl_change_percentage": 35199.52685,
		"atl_date": "2019-05-10T00:00:00.000Z",
		"circulating_supply": 9080469069.28493,
		"current_price": 1.11,
		"fully_diluted_valuation": 11117752595,
		"high_24h": 1.14,
		"id": "matic-network",
		"image": "https://assets.coingecko.com/coins/images/4713/large/matic-token-icon.png?1624446912",
		"last_updated": "2023-03-30T09:53:54.487Z",
		"low_24h": 1.11,
		"market_cap": 10095440856,
		"market_cap_change_24h": -262691121.333807,
		"market_cap_change_percentage_24h": -2.53609,
		"market_cap_rank": 10,
		"max_supply": 10000000000,
		"name": "Polygon",
		"price_change_24h": -0.027939091868209864,
		"price_change_percentage_24h": -2.45067,
		"roi": {
			"currency": "usd",
			"percentage": 42185.99393625346,
			"times": 421.8599393625346
		},
		"symbol": "matic",
		"total_supply": 10000000000,
		"total_volume": 417472909
	},
	{
		"ath": 1.15,
		"ath_change_percentage": -13.32447,
		"ath_date": "2020-03-13T02:35:42.953Z",
		"atl": 0.901127,
		"atl_change_percentage": 11.0179,
		"atl_date": "2021-05-19T13:04:37.445Z",
		"circulating_supply": 7664673849,
		"current_price": 1.001,
		"fully_diluted_valuation": 7671336139,
		"high_24h": 1.011,
		"id": "binance-usd",
		"image": "https://assets.coingecko.com/coins/images/9576/large/BUSD.png?1568947766",
		"last_updated": "2023-03-30T09:53:56.390Z",
		"low_24h": 0.995729,
		"market_cap": 7671336139,
		"market_cap_change_24h": -16860693.203196526,
		"market_cap_change_percentage_24h": -0.21931,
		"market_cap_rank": 12,
		"max_supply": null,
		"name": "Binance USD",
		"price_change_24h": 0.00341253,
		"price_change_percentage_24h": 0.34216,
		"roi": null,
		"symbol": "busd",
		"total_supply": 7664673849,
		"total_volume": 4396148456
	},
	{
		"ath": 0.00008616,
		"ath_change_percentage": -87.6782,
		"ath_date": "2021-10-28T03:54:55.568Z",
		"atl": 5.6366e-11,
		"atl_change_percentage": 18834374.36502,
		"atl_date": "2020-11-28T11:26:25.838Z",
		"circulating_supply": 589359535804380.8,
		"current_price": 0.00001063,
		"fully_diluted_valuation": null,
		"high_24h": 0.00001081,
		"id": "shiba-inu",
		"image": "https://assets.coingecko.com/coins/images/11939/large/shiba.png?1622619446",
		"last_updated": "2023-03-30T09:53:53.110Z",
		"low_24h": 0.00001056,
		"market_cap": 6260823794,
		"market_cap_change_24h": -92017525.51805496,
		"market_cap_change_percentage_24h": -1.44845,
		"market_cap_rank": 15,
		"max_supply": null,
		"name": "Shiba Inu",
		"price_change_24h": -1.53093801071e-7,
		"price_change_percentage_24h": -1.4202,
		"roi": null,
		"symbol": "shib",
		"total_supply": 999990903807043,
		"total_volume": 240281498
	},
	{
		"ath": 1.22,
		"ath_change_percentage": -18.02092,
		"ath_date": "2020-03-13T03:02:50.373Z",
		"atl": 0.88196,
		"atl_change_percentage": 13.30085,
		"atl_date": "2023-03-11T07:50:50.514Z",
		"circulating_supply": 5101926133.79904,
		"current_price": 1,
		"fully_diluted_valuation": 5104379600,
		"high_24h": 1.003,
		"id": "dai",
		"image": "https://assets.coingecko.com/coins/images/9956/large/4943.png?1636636734",
		"last_updated": "2023-03-30T09:50:02.446Z",
		"low_24h": 0.994674,
		"market_cap": 5104367094,
		"market_cap_change_24h": -5102874.9870939255,
		"market_cap_change_percentage_24h": -0.09987,
		"market_cap_rank": 18,
		"max_supply": 5101938633.79904,
		"name": "Dai",
		"price_change_24h": 0.00206578,
		"price_change_percentage_24h": 0.20691,
		"roi": null,
		"symbol": "dai",
		"total_supply": 5101938633.79904,
		"total_volume": 157618904
	},
	{
		"ath": 44.92,
		"ath_change_percentage": -86.90923,
		"ath_date": "2021-05-03T05:25:04.822Z",
		"atl": 1.03,
		"atl_change_percentage": 470.79076,
		"atl_date": "2020-09-17T01:20:38.214Z",
		"circulating_supply": 753766667,
		"current_price": 5.89,
		"fully_diluted_valuation": 5890140093,
		"high_24h": 6.05,
		"id": "uniswap",
		"image": "https://assets.coingecko.com/coins/images/12504/large/uniswap-uni.png?1600306604",
		"last_updated": "2023-03-30T09:53:56.855Z",
		"low_24h": 5.87,
		"market_cap": 4439791266,
		"market_cap_change_24h": -75377071.47890377,
		"market_cap_change_percentage_24h": -1.66942,
		"market_cap_rank": 19,
		"max_supply": 1000000000,
		"name": "Uniswap",
		"price_change_24h": -0.09814064767276687,
		"price_change_percentage_24h": -1.6385,
		"roi": null,
		"symbol": "uni",
		"total_supply": 1000000000,
		"total_volume": 75544054
	},
	{
		"ath": 70643,
		"ath_change_percentage": -59.5846,
		"ath_date": "2021-11-10T14:40:19.650Z",
		"atl": 3139.17,
		"atl_change_percentage": 809.50107,
		"atl_date": "2019-04-02T00:00:00.000Z",
		"circulating_supply": 150450.1842313,
		"current_price": 28563,
		"fully_diluted_valuation": 4297854318,
		"high_24h": 29097,
		"id": "wrapped-bitcoin",
		"image": "https://assets.coingecko.com/coins/images/7598/large/wrapped_bitcoin_wbtc.png?1548822744",
		"last_updated": "2023-03-30T09:53:54.044Z",
		"low_24h": 28240,
		"market_cap": 4297854318,
		"market_cap_change_24h": 29987888,
		"market_cap_change_percentage_24h": 0.70264,
		"market_cap_rank": 20,
		"max_supply": 150450.1842313,
		"name": "Wrapped Bitcoin",
		"price_change_24h": 198.65,
		"price_change_percentage_24h": 0.70033,
		"roi": null,
		"symbol": "wbtc",
		"total_supply": 150450.1842313,
		"total_volume": 178847466
	},
	{
		"ath": 52.7,
		"ath_change_percentage": -86.10722,
		"ath_date": "2021-05-10T00:13:57.214Z",
		"atl": 0.148183,
		"atl_change_percentage": 4840.52014,
		"atl_date": "2017-11-29T00:00:00.000Z",
		"circulating_supply": 517099971.2305644,
		"current_price": 7.34,
		"fully_diluted_valuation": 7334518079,
		"high_24h": 7.53,
		"id": "chainlink",
		"image": "https://assets.coingecko.com/coins/images/877/large/chainlink-new-logo.png?1547034700",
		"last_updated": "2023-03-30T09:54:01.101Z",
		"low_24h": 7.24,
		"market_cap": 3792679088,
		"market_cap_change_24h": 196191809,
		"market_cap_change_percentage_24h": 5.4551,
		"market_cap_rank": 21,
		"max_supply": 1000000000,
		"name": "Chainlink",
		"price_change_24h": 0.02545124,
		"price_change_percentage_24h": 0.34813,
		"roi": null,
		"symbol": "link",
		"total_supply": 1000000000,
		"total_volume": 376048292
	},
	{
		"ath": 8.14,
		"ath_change_percentage": -58.03344,
		"ath_date": "2022-02-08T17:40:10.285Z",
		"atl": 0.799859,
		"atl_change_percentage": 326.84061,
		"atl_date": "2019-12-24T15:14:35.376Z",
		"circulating_supply": 930936300.9,
		"current_price": 3.42,
		"fully_diluted_valuation": null,
		"high_24h": 3.44,
		"id": "leo-token",
		"image": "https://assets.coingecko.com/coins/images/8418/large/leo-token.png?1558326215",
		"last_updated": "2023-03-30T09:53:11.527Z",
		"low_24h": 3.4,
		"market_cap": 3179817271,
		"market_cap_change_24h": 12012286,
		"market_cap_change_percentage_24h": 0.3792,
		"market_cap_rank": 23,
		"max_supply": null,
		"name": "LEO Token",
		"price_change_24h": 0.01445977,
		"price_change_percentage_24h": 0.42509,
		"roi": null,
		"symbol": "leo",
		"total_supply": 985239504,
		"total_volume": 364884
	},
	{
		"ath": 5.29,
		"ath_change_percentage": -60.43154,
		"ath_date": "2021-11-12T06:50:02.476Z",
		"atl": 0.519364,
		"atl_change_percentage": 303.08663,
		"atl_date": "2021-09-21T00:33:11.092Z",
		"circulating_supply": 1473591410.74313,
		"current_price": 2.1,
		"fully_diluted_valuation": 10597881902,
		"high_24h": 2.18,
		"id": "the-open-network",
		"image": "https://assets.coingecko.com/coins/images/17980/large/ton_symbol.png?1670498136",
		"last_updated": "2023-03-30T09:54:00.988Z",
		"low_24h": 2.08,
		"market_cap": 3087962727,
		"market_cap_change_24h": -8529898.866044998,
		"market_cap_change_percentage_24h": -0.27547,
		"market_cap_rank": 24,
		"max_supply": null,
		"name": "Toncoin",
		"price_change_24h": -0.005265116271625737,
		"price_change_percentage_24h": -0.25028,
		"roi": null,
		"symbol": "ton",
		"total_supply": 5057362773.99687,
		"total_volume": 19981027
	},
	{
		"ath": 58.66,
		"ath_change_percentage": -27.7694,
		"ath_date": "2023-02-18T01:21:37.582Z",
		"atl": 0.580608,
		"atl_change_percentage": 7197.43316,
		"atl_date": "2019-01-14T00:00:00.000Z",
		"circulating_supply": 60000000,
		"current_price": 42.41,
		"fully_diluted_valuation": 12725749015,
		"high_24h": 43.4,
		"id": "okb",
		"image": "https://assets.coingecko.com/coins/images/4463/large/WeChat_Image_20220118095654.png?1642471050",
		"last_updated": "2023-03-30T09:53:49.531Z",
		"low_24h": 42.31,
		"market_cap": 2545149803,
		"market_cap_change_24h": -58715606.46767187,
		"market_cap_change_percentage_24h": -2.25494,
		"market_cap_rank": 28,
		"max_supply": 300000000,
		"name": "OKB",
		"price_change_24h": -0.8437000681739448,
		"price_change_percentage_24h": -1.95038,
		"roi": null,
		"symbol": "okb",
		"total_supply": 246638974,
		"total_volume": 36919908
	},
	{
		"ath": 1.62,
		"ath_change_percentage": -38.20072,
		"ath_date": "2018-08-26T20:41:09.375Z",
		"atl": 0.88355,
		"atl_change_percentage": 13.20575,
		"atl_date": "2020-03-12T10:47:51.380Z",
		"circulating_supply": 2041446767.12,
		"current_price": 1.001,
		"fully_diluted_valuation": null,
		"high_24h": 1.006,
		"id": "true-usd",
		"image": "https://assets.coingecko.com/coins/images/3449/large/tusd.png?1618395665",
		"last_updated": "2023-03-30T09:53:57.979Z",
		"low_24h": 0.984566,
		"market_cap": 2044328625,
		"market_cap_change_24h": 7577613,
		"market_cap_change_percentage_24h": 0.37204,
		"market_cap_rank": 31,
		"max_supply": null,
		"name": "TrueUSD",
		"price_change_24h": 0.00191672,
		"price_change_percentage_24h": 0.19179,
		"roi": null,
		"symbol": "tusd",
		"total_supply": 2041446767.12,
		"total_volume": 891258092
	},
	{
		"ath": 7.3,
		"ath_change_percentage": -67.9905,
		"ath_date": "2021-08-20T08:35:20.158Z",
		"atl": 0.40615,
		"atl_change_percentage": 475.55433,
		"atl_date": "2022-06-18T20:55:12.035Z",
		"circulating_supply": 861661882.450563,
		"current_price": 2.34,
		"fully_diluted_valuation": 2340817134,
		"high_24h": 2.49,
		"id": "lido-dao",
		"image": "https://assets.coingecko.com/coins/images/13573/large/Lido_DAO.png?1609873644",
		"last_updated": "2023-03-30T09:53:59.805Z",
		"low_24h": 2.34,
		"market_cap": 2016992898,
		"market_cap_change_24h": -60470923.472071886,
		"market_cap_change_percentage_24h": -2.91081,
		"market_cap_rank": 32,
		"max_supply": 1000000000,
		"name": "Lido DAO",
		"price_change_24h": -0.06957377538126375,
		"price_change_percentage_24h": -2.88532,
		"roi": null,
		"symbol": "ldo",
		"total_supply": 1000000000,
		"total_volume": 140034287
	},
	{
		"ath": 427.42,
		"ath_change_percentage": -70.65007,
		"ath_date": "2021-09-11T09:15:00.668Z",
		"atl": 0.215773,
		"atl_change_percentage": 58038.85968,
		"atl_date": "2018-08-23T00:00:00.000Z",
		"circulating_supply": 14544176.164091088,
		"current_price": 125.73,
		"fully_diluted_valuation": 1835932004,
		"high_24h": 127.39,
		"id": "quant-network",
		"image": "https://assets.coingecko.com/coins/images/3370/large/5ZOu7brX_400x400.jpg?1612437252",
		"last_updated": "2023-03-30T09:53:54.446Z",
		"low_24h": 121.77,
		"market_cap": 1827348591,
		"market_cap_change_24h": 48922509,
		"market_cap_change_percentage_24h": 2.75089,
		"market_cap_rank": 35,
		"max_supply": 14612493,
		"name": "Quant",
		"price_change_24h": 3.65,
		"price_change_percentage_24h": 2.99121,
		"roi": {
			"currency": "eth",
			"percentage": 2903.672426913077,
			"times": 29.03672426913077
		},
		"symbol": "qnt",
		"total_supply": 14612493,
		"total_volume": 32440799
	},
	{
		"ath": 8.67,
		"ath_change_percentage": -84.07443,
		"ath_date": "2023-03-23T13:10:03.106Z",
		"atl": 1.11,
		"atl_change_percentage": 24.91874,
		"atl_date": "2023-03-23T14:35:24.485Z",
		"circulating_supply": 1275000000,
		"current_price": 1.38,
		"fully_diluted_valuation": 13822911875,
		"high_24h": 1.42,
		"id": "arbitrum",
		"image": "https://assets.coingecko.com/coins/images/16547/large/photo_2023-03-29_21.47.00.jpeg?1680097630",
		"last_updated": "2023-03-30T09:54:01.669Z",
		"low_24h": 1.2,
		"market_cap": 1762421264,
		"market_cap_change_24h": 159265245,
		"market_cap_change_percentage_24h": 9.93448,
		"market_cap_rank": 36,
		"max_supply": 10000000000,
		"name": "Arbitrum",
		"price_change_24h": 0.124491,
		"price_change_percentage_24h": 9.9064,
		"roi": null,
		"symbol": "arb",
		"total_supply": 10000000000,
		"total_volume": 1323536413
	},
	{
		"ath": 0.965407,
		"ath_change_percentage": -92.85735,
		"ath_date": "2021-11-24T15:53:54.855Z",
		"atl": 0.0121196,
		"atl_change_percentage": 468.96026,
		"atl_date": "2019-02-08T00:00:00.000Z",
		"circulating_supply": 25263013692,
		"current_price": 0.069015,
		"fully_diluted_valuation": null,
		"high_24h": 0.07018,
		"id": "crypto-com-chain",
		"image": "https://assets.coingecko.com/coins/images/7310/large/cro_token_logo.png?1669699773",
		"last_updated": "2023-03-30T09:54:00.109Z",
		"low_24h": 0.068416,
		"market_cap": 1743214643,
		"market_cap_change_24h": 12946963,
		"market_cap_change_percentage_24h": 0.74826,
		"market_cap_rank": 37,
		"max_supply": null,
		"name": "Cronos",
		"price_change_24h": 0.00059121,
		"price_change_percentage_24h": 0.86405,
		"roi": null,
		"symbol": "cro",
		"total_supply": 30263013692,
		"total_volume": 19002794
	},
	{
		"ath": 26.7,
		"ath_change_percentage": -84.65008,
		"ath_date": "2022-04-28T21:44:21.164Z",
		"atl": 2.63,
		"atl_change_percentage": 56.05002,
		"atl_date": "2022-11-14T04:22:00.792Z",
		"circulating_supply": 368593750,
		"current_price": 4.1,
		"fully_diluted_valuation": 4090702764,
		"high_24h": 4.21,
		"id": "apecoin",
		"image": "https://assets.coingecko.com/coins/images/24383/large/apecoin.jpg?1647476455",
		"last_updated": "2023-03-30T09:53:55.518Z",
		"low_24h": 4.04,
		"market_cap": 1507807472,
		"market_cap_change_24h": -40984208.56528187,
		"market_cap_change_percentage_24h": -2.64621,
		"market_cap_rank": 41,
		"max_supply": 1000000000,
		"name": "ApeCoin",
		"price_change_24h": -0.10744760338168911,
		"price_change_percentage_24h": -2.55671,
		"roi": null,
		"symbol": "ape",
		"total_supply": 1000000000,
		"total_volume": 130941773
	},
	{
		"ath": 2.84,
		"ath_change_percentage": -94.9201,
		"ath_date": "2021-02-12T07:28:45.775Z",
		"atl": 0.052051,
		"atl_change_percentage": 177.31562,
		"atl_date": "2022-11-22T10:05:03.503Z",
		"circulating_supply": 8888950627.50468,
		"current_price": 0.144652,
		"fully_diluted_valuation": 1445488592,
		"high_24h": 0.150579,
		"id": "the-graph",
		"image": "https://assets.coingecko.com/coins/images/13397/large/Graph_Token.png?1608145566",
		"last_updated": "2023-03-30T09:53:51.343Z",
		"low_24h": 0.144183,
		"market_cap": 1284887673,
		"market_cap_change_24h": -35262106.011832476,
		"market_cap_change_percentage_24h": -2.67107,
		"market_cap_rank": 44,
		"max_supply": null,
		"name": "The Graph",
		"price_change_24h": -0.003359673630142196,
		"price_change_percentage_24h": -2.26987,
		"roi": null,
		"symbol": "grt",
		"total_supply": 10000000000,
		"total_volume": 87314974
	},
	{
		"ath": 3.46,
		"ath_change_percentage": -87.01849,
		"ath_date": "2021-10-28T05:19:39.845Z",
		"atl": 0.00190227,
		"atl_change_percentage": 23502.07449,
		"atl_date": "2020-03-13T02:25:38.280Z",
		"circulating_supply": 2783670220.67357,
		"current_price": 0.450128,
		"fully_diluted_valuation": 1428536331,
		"high_24h": 0.469957,
		"id": "fantom",
		"image": "https://assets.coingecko.com/coins/images/4001/large/Fantom_round.png?1669652346",
		"last_updated": "2023-03-30T09:53:56.416Z",
		"low_24h": 0.448644,
		"market_cap": 1252464265,
		"market_cap_change_24h": -29979571.39568448,
		"market_cap_change_percentage_24h": -2.33769,
		"market_cap_rank": 46,
		"max_supply": 3175000000,
		"name": "Fantom",
		"price_change_24h": -0.010679607937196913,
		"price_change_percentage_24h": -2.31759,
		"roi": {
			"currency": "usd",
			"percentage": 1400.425778622368,
			"times": 14.00425778622368
		},
		"symbol": "ftm",
		"total_supply": 3175000000,
		"total_volume": 436719382
	},
	{
		"ath": 8.4,
		"ath_change_percentage": -92.59256,
		"ath_date": "2021-11-25T06:04:40.957Z",
		"atl": 0.02897764,
		"atl_change_percentage": 2046.44119,
		"atl_date": "2020-11-04T15:59:14.441Z",
		"circulating_supply": 1820281926.2233226,
		"current_price": 0.619292,
		"fully_diluted_valuation": 1866785849,
		"high_24h": 0.647693,
		"id": "the-sandbox",
		"image": "https://assets.coingecko.com/coins/images/12129/large/sandbox_logo.jpg?1597397942",
		"last_updated": "2023-03-30T09:53:55.974Z",
		"low_24h": 0.619401,
		"market_cap": 1132692180,
		"market_cap_change_24h": -38865344.84077263,
		"market_cap_change_percentage_24h": -3.31741,
		"market_cap_rank": 47,
		"max_supply": 3000000000,
		"name": "The Sandbox",
		"price_change_24h": -0.02390210638827228,
		"price_change_percentage_24h": -3.71616,
		"roi": null,
		"symbol": "sand",
		"total_supply": 3000000000,
		"total_volume": 99693898
	},
	{
		"ath": 5.85,
		"ath_change_percentage": -90.01774,
		"ath_date": "2021-11-25T10:04:18.534Z",
		"atl": 0.00923681,
		"atl_change_percentage": 6223.01061,
		"atl_date": "2017-10-31T00:00:00.000Z",
		"circulating_supply": 1824385640.3915346,
		"current_price": 0.584683,
		"fully_diluted_valuation": 1282809219,
		"high_24h": 0.606091,
		"id": "decentraland",
		"image": "https://assets.coingecko.com/coins/images/878/large/decentraland-mana.png?1550108745",
		"last_updated": "2023-03-30T09:54:01.354Z",
		"low_24h": 0.583099,
		"market_cap": 1067095107,
		"market_cap_change_24h": -27460433.026621222,
		"market_cap_change_percentage_24h": -2.50882,
		"market_cap_rank": 49,
		"max_supply": 2193186627.32015,
		"name": "Decentraland",
		"price_change_24h": -0.014048966467775427,
		"price_change_percentage_24h": -2.34645,
		"roi": {
			"currency": "usd",
			"percentage": 2823.4132330234415,
			"times": 28.234132330234416
		},
		"symbol": "mana",
		"total_supply": 2193186627.32015,
		"total_volume": 97820891
	},
	{
		"ath": 1.14,
		"ath_change_percentage": -12.51736,
		"ath_date": "2021-02-07T12:55:35.766Z",
		"atl": 0.874536,
		"atl_change_percentage": 14.08294,
		"atl_date": "2023-03-11T07:50:39.316Z",
		"circulating_supply": 1044853133.25878,
		"current_price": 0.998283,
		"fully_diluted_valuation": 1043347020,
		"high_24h": 1.005,
		"id": "frax",
		"image": "https://assets.coingecko.com/coins/images/13422/large/FRAX_icon.png?1679886922",
		"last_updated": "2023-03-30T09:53:51.502Z",
		"low_24h": 0.992048,
		"market_cap": 1043347020,
		"market_cap_change_24h": -994427.5737059116,
		"market_cap_change_percentage_24h": -0.09522,
		"market_cap_rank": 50,
		"max_supply": 1044853133.25878,
		"name": "Frax",
		"price_change_24h": -0.001330838374227983,
		"price_change_percentage_24h": -0.13314,
		"roi": null,
		"symbol": "frax",
		"total_supply": 1044853133.25878,
		"total_volume": 10133627
	},
	{
		"ath": 661.69,
		"ath_change_percentage": -89.13658,
		"ath_date": "2021-05-18T21:19:59.514Z",
		"atl": 26.02,
		"atl_change_percentage": 176.22405,
		"atl_date": "2020-11-05T09:20:11.928Z",
		"circulating_supply": 14335158.60242846,
		"current_price": 72,
		"fully_diluted_valuation": 1151080569,
		"high_24h": 74.15,
		"id": "aave",
		"image": "https://assets.coingecko.com/coins/images/12645/large/AAVE.png?1601374110",
		"last_updated": "2023-03-30T09:53:56.310Z",
		"low_24h": 71.86,
		"market_cap": 1031307658,
		"market_cap_change_24h": -12162269.494211316,
		"market_cap_change_percentage_24h": -1.16556,
		"market_cap_rank": 51,
		"max_supply": 16000000,
		"name": "Aave",
		"price_change_24h": -0.7882727121367452,
		"price_change_percentage_24h": -1.08292,
		"roi": null,
		"symbol": "aave",
		"total_supply": 16000000,
		"total_volume": 54967540
	},
	{
		"ath": 9.52,
		"ath_change_percentage": -88.45305,
		"ath_date": "2021-11-26T01:03:01.536Z",
		"atl": 0.378055,
		"atl_change_percentage": 190.76789,
		"atl_date": "2022-12-31T07:36:37.649Z",
		"circulating_supply": 914163545.5400242,
		"current_price": 1.1,
		"fully_diluted_valuation": 2200671865,
		"high_24h": 1.18,
		"id": "immutable-x",
		"image": "https://assets.coingecko.com/coins/images/17233/large/immutableX-symbol-BLK-RGB.png?1665110648",
		"last_updated": "2023-03-30T09:53:54.696Z",
		"low_24h": 1.094,
		"market_cap": 1005886997,
		"market_cap_change_24h": -59267732.267615914,
		"market_cap_change_percentage_24h": -5.56424,
		"market_cap_rank": 55,
		"max_supply": 2000000000,
		"name": "ImmutableX",
		"price_change_24h": -0.06976968988868082,
		"price_change_percentage_24h": -5.96126,
		"roi": null,
		"symbol": "imx",
		"total_supply": 2000000000,
		"total_volume": 50839369
	},
	{
		"ath": 164.9,
		"ath_change_percentage": -94.94942,
		"ath_date": "2021-11-06T19:29:29.482Z",
		"atl": 0.123718,
		"atl_change_percentage": 6631.66351,
		"atl_date": "2020-11-06T08:05:43.662Z",
		"circulating_supply": 115661358.61362292,
		"current_price": 8.35,
		"fully_diluted_valuation": 2251050283,
		"high_24h": 8.64,
		"id": "axie-infinity",
		"image": "https://assets.coingecko.com/coins/images/13029/large/axie_infinity_logo.png?1604471082",
		"last_updated": "2023-03-30T09:53:53.106Z",
		"low_24h": 8.31,
		"market_cap": 964294571,
		"market_cap_change_24h": -22955940.70698726,
		"market_cap_change_percentage_24h": -2.32524,
		"market_cap_rank": 56,
		"max_supply": 270000000,
		"name": "Axie Infinity",
		"price_change_24h": -0.18838678971277467,
		"price_change_percentage_24h": -2.20679,
		"roi": null,
		"symbol": "axs",
		"total_supply": 270000000,
		"total_volume": 51401563
	},
	{
		"ath": 59.46,
		"ath_change_percentage": -24.89215,
		"ath_date": "2021-11-09T04:03:31.003Z",
		"atl": 0.00884718,
		"atl_change_percentage": 504648.40552,
		"atl_date": "2018-08-28T00:00:00.000Z",
		"circulating_supply": 19257025.5471179,
		"current_price": 44.71,
		"fully_diluted_valuation": null,
		"high_24h": 46.44,
		"id": "rocket-pool",
		"image": "https://assets.coingecko.com/coins/images/2090/large/rocket_pool_%28RPL%29.png?1637662441",
		"last_updated": "2023-03-30T09:53:57.816Z",
		"low_24h": 44.66,
		"market_cap": 860724812,
		"market_cap_change_24h": -31348551.13817954,
		"market_cap_change_percentage_24h": -3.51412,
		"market_cap_rank": 60,
		"max_supply": null,
		"name": "Rocket Pool",
		"price_change_24h": -1.6424163128715108,
		"price_change_percentage_24h": -3.54317,
		"roi": null,
		"symbol": "rpl",
		"total_supply": 19257025.5471179,
		"total_volume": 6276627
	},
	{
		"ath": 28.53,
		"ath_change_percentage": -91.37193,
		"ath_date": "2021-02-14T01:12:38.505Z",
		"atl": 0.0347864,
		"atl_change_percentage": 6976.86216,
		"atl_date": "2019-01-06T00:00:00.000Z",
		"circulating_supply": 315614653.13952357,
		"current_price": 2.47,
		"fully_diluted_valuation": 781546862,
		"high_24h": 2.58,
		"id": "havven",
		"image": "https://assets.coingecko.com/coins/images/3406/large/SNX.png?1598631139",
		"last_updated": "2023-03-30T09:53:52.911Z",
		"low_24h": 2.45,
		"market_cap": 779758373,
		"market_cap_change_24h": -4635902.958049297,
		"market_cap_change_percentage_24h": -0.59102,
		"market_cap_rank": 62,
		"max_supply": 316338561.088774,
		"name": "Synthetix Network",
		"price_change_24h": -0.011341471581012287,
		"price_change_percentage_24h": -0.45656,
		"roi": {
			"currency": "usd",
			"percentage": 394.5501114184592,
			"times": 3.945501114184592
		},
		"symbol": "snx",
		"total_supply": 316338561.088774,
		"total_volume": 73059558
	},
	{
		"ath": 14.64,
		"ath_change_percentage": -63.55266,
		"ath_date": "2022-10-28T12:32:18.119Z",
		"atl": 3.06,
		"atl_change_percentage": 74.33275,
		"atl_date": "2023-02-13T19:01:21.899Z",
		"circulating_supply": 144118517.10815412,
		"current_price": 5.35,
		"fully_diluted_valuation": 2141815777,
		"high_24h": 5.36,
		"id": "whitebit",
		"image": "https://assets.coingecko.com/coins/images/27045/large/wbt_token.png?1667923752",
		"last_updated": "2023-03-30T09:54:00.494Z",
		"low_24h": 5.19,
		"market_cap": 771688284,
		"market_cap_change_24h": 16138877,
		"market_cap_change_percentage_24h": 2.13605,
		"market_cap_rank": 63,
		"max_supply": 400000000,
		"name": "WhiteBIT Token",
		"price_change_24h": 0.096451,
		"price_change_percentage_24h": 1.83526,
		"roi": null,
		"symbol": "wbt",
		"total_supply": 377982163,
		"total_volume": 10506414
	},
	{
		"ath": 1.13,
		"ath_change_percentage": -11.22086,
		"ath_date": "2018-10-15T07:09:12.459Z",
		"atl": 0.863529,
		"atl_change_percentage": 15.93588,
		"atl_date": "2021-05-19T13:14:42.046Z",
		"circulating_supply": 757552716.460683,
		"current_price": 1.001,
		"fully_diluted_valuation": 758664242,
		"high_24h": 1.025,
		"id": "paxos-standard",
		"image": "https://assets.coingecko.com/coins/images/6013/large/Pax_Dollar.png?1629877204",
		"last_updated": "2023-03-30T09:54:00.694Z",
		"low_24h": 0.987492,
		"market_cap": 758664242,
		"market_cap_change_24h": 1421037,
		"market_cap_change_percentage_24h": 0.18766,
		"market_cap_rank": 64,
		"max_supply": null,
		"name": "Pax Dollar",
		"price_change_24h": 0.0031341,
		"price_change_percentage_24h": 0.31409,
		"roi": {
			"currency": "usd",
			"percentage": 0.0970786154095,
			"times": 0.000970786154095
		},
		"symbol": "usdp",
		"total_supply": 757552716.460683,
		"total_volume": 3703913
	},
	{
		"ath": 3.1,
		"ath_change_percentage": -82.97572,
		"ath_date": "2021-11-12T04:54:56.433Z",
		"atl": 0.270167,
		"atl_change_percentage": 95.48103,
		"atl_date": "2022-11-22T08:40:21.230Z",
		"circulating_supply": 1433909320.2107098,
		"current_price": 0.527871,
		"fully_diluted_valuation": 5075582305,
		"high_24h": 0.53658,
		"id": "bitdao",
		"image": "https://assets.coingecko.com/coins/images/17627/large/rI_YptK8.png?1653983088",
		"last_updated": "2023-03-30T09:54:01.776Z",
		"low_24h": 0.526459,
		"market_cap": 757309414,
		"market_cap_change_24h": -9005466.432833433,
		"market_cap_change_percentage_24h": -1.17517,
		"market_cap_rank": 65,
		"max_supply": 9610239403,
		"name": "BitDAO",
		"price_change_24h": -0.006336007945608513,
		"price_change_percentage_24h": -1.18606,
		"roi": null,
		"symbol": "bit",
		"total_supply": 9610239403,
		"total_volume": 5211954
	},
	{
		"ath": 15.37,
		"ath_change_percentage": -93.90723,
		"ath_date": "2020-08-14T00:00:00.000Z",
		"atl": 0.331577,
		"atl_change_percentage": 182.46435,
		"atl_date": "2020-11-05T13:09:50.181Z",
		"circulating_supply": 772104182,
		"current_price": 0.937605,
		"fully_diluted_valuation": 3096722687,
		"high_24h": 0.961029,
		"id": "curve-dao-token",
		"image": "https://assets.coingecko.com/coins/images/12124/large/Curve.png?1597369484",
		"last_updated": "2023-03-30T09:53:56.128Z",
		"low_24h": 0.931789,
		"market_cap": 723878476,
		"market_cap_change_24h": -12516421.54987073,
		"market_cap_change_percentage_24h": -1.69969,
		"market_cap_rank": 67,
		"max_supply": 3303030299,
		"name": "Curve DAO",
		"price_change_24h": -0.016760148679556,
		"price_change_percentage_24h": -1.75616,
		"roi": null,
		"symbol": "crv",
		"total_supply": 1924248900.98946,
		"total_volume": 46286872
	},
	{
		"ath": 1.044,
		"ath_change_percentage": -5.33287,
		"ath_date": "2022-11-09T09:56:06.131Z",
		"atl": 0.928067,
		"atl_change_percentage": 6.48382,
		"atl_date": "2022-06-19T16:15:11.558Z",
		"circulating_supply": 725332035.842248,
		"current_price": 0.988184,
		"fully_diluted_valuation": null,
		"high_24h": 0.993824,
		"id": "usdd",
		"image": "https://assets.coingecko.com/coins/images/25380/large/UUSD.jpg?1651823371",
		"last_updated": "2023-03-30T09:53:54.638Z",
		"low_24h": 0.985591,
		"market_cap": 716580926,
		"market_cap_change_24h": -2049218.1152875423,
		"market_cap_change_percentage_24h": -0.28516,
		"market_cap_rank": 69,
		"max_supply": null,
		"name": "USDD",
		"price_change_24h": -0.00256347805368673,
		"price_change_percentage_24h": -0.25874,
		"roi": null,
		"symbol": "usdd",
		"total_supply": null,
		"total_volume": 28407727
	},
	{
		"ath": 12.94,
		"ath_change_percentage": -61.15344,
		"ath_date": "2021-05-12T11:39:16.531Z",
		"atl": 0.25754,
		"atl_change_percentage": 1852.10939,
		"atl_date": "2020-03-13T02:18:02.481Z",
		"circulating_supply": 140973058.65504882,
		"current_price": 5.02,
		"fully_diluted_valuation": null,
		"high_24h": 5.16,
		"id": "gatechain-token",
		"image": "https://assets.coingecko.com/coins/images/8183/large/gt.png?1556085624",
		"last_updated": "2023-03-30T09:53:31.994Z",
		"low_24h": 4.99,
		"market_cap": 708106839,
		"market_cap_change_24h": -18205768.90697205,
		"market_cap_change_percentage_24h": -2.5066,
		"market_cap_rank": 71,
		"max_supply": null,
		"name": "Gate",
		"price_change_24h": -0.12681728213853916,
		"price_change_percentage_24h": -2.46266,
		"roi": null,
		"symbol": "gt",
		"total_supply": 300000000,
		"total_volume": 626084
	},
	{
		"ath": 42.8,
		"ath_change_percentage": -79.48618,
		"ath_date": "2022-01-12T15:22:27.465Z",
		"atl": 1.5,
		"atl_change_percentage": 484.09414,
		"atl_date": "2021-06-25T16:50:51.447Z",
		"circulating_supply": 71106103.0230072,
		"current_price": 8.77,
		"fully_diluted_valuation": 875797877,
		"high_24h": 9.01,
		"id": "frax-share",
		"image": "https://assets.coingecko.com/coins/images/13423/large/Frax_Shares_icon.png?1679886947",
		"last_updated": "2023-03-30T09:53:52.809Z",
		"low_24h": 8.61,
		"market_cap": 623850054,
		"market_cap_change_24h": -7164850.58249104,
		"market_cap_change_percentage_24h": -1.13545,
		"market_cap_rank": 77,
		"max_supply": 99822984.1145714,
		"name": "Frax Share",
		"price_change_24h": -0.11738247628233367,
		"price_change_percentage_24h": -1.32107,
		"roi": null,
		"symbol": "fxs",
		"total_supply": 99822984.1145714,
		"total_volume": 33683026
	},
	{
		"ath": 0.878633,
		"ath_change_percentage": -86.78192,
		"ath_date": "2021-03-13T08:04:21.200Z",
		"atl": 0.00410887,
		"atl_change_percentage": 2726.5277,
		"atl_date": "2019-09-28T00:00:00.000Z",
		"circulating_supply": 5344064580,
		"current_price": 0.116548,
		"fully_diluted_valuation": 1035613089,
		"high_24h": 0.121112,
		"id": "chiliz",
		"image": "https://assets.coingecko.com/coins/images/8834/large/CHZ_Token_updated.png?1675848257",
		"last_updated": "2023-03-30T09:54:01.230Z",
		"low_24h": 0.116059,
		"market_cap": 622618113,
		"market_cap_change_24h": -12749171.800441384,
		"market_cap_change_percentage_24h": -2.00658,
		"market_cap_rank": 78,
		"max_supply": 8888888888,
		"name": "Chiliz",
		"price_change_24h": -0.002278577446856653,
		"price_change_percentage_24h": -1.91757,
		"roi": {
			"currency": "usd",
			"percentage": 429.76164343516547,
			"times": 4.297616434351655
		},
		"symbol": "chz",
		"total_supply": 8888888888,
		"total_volume": 93635200
	},
	{
		"ath": 6292.31,
		"ath_change_percentage": -89.19944,
		"ath_date": "2021-05-03T21:54:29.333Z",
		"atl": 168.36,
		"atl_change_percentage": 303.66784,
		"atl_date": "2020-03-16T20:52:36.527Z",
		"circulating_supply": 901310.9472893132,
		"current_price": 680.28,
		"fully_diluted_valuation": 684123573,
		"high_24h": 703.91,
		"id": "maker",
		"image": "https://assets.coingecko.com/coins/images/1364/large/Mark_Maker.png?1585191826",
		"last_updated": "2023-03-30T09:53:51.495Z",
		"low_24h": 678.09,
		"market_cap": 613188314,
		"market_cap_change_24h": -8884031.137249708,
		"market_cap_change_percentage_24h": -1.42813,
		"market_cap_rank": 79,
		"max_supply": 1005577,
		"name": "Maker",
		"price_change_24h": -7.156276596308203,
		"price_change_percentage_24h": -1.04101,
		"roi": null,
		"symbol": "mkr",
		"total_supply": 977631.036950888,
		"total_volume": 43731808
	},
	{
		"ath": 39.66,
		"ath_change_percentage": -90.70154,
		"ath_date": "2021-05-12T14:42:21.586Z",
		"atl": 0.90862,
		"atl_change_percentage": 305.87265,
		"atl_date": "2019-01-30T00:00:00.000Z",
		"circulating_supply": 162336522.3,
		"current_price": 3.68,
		"fully_diluted_valuation": 750515561,
		"high_24h": 3.71,
		"id": "huobi-token",
		"image": "https://assets.coingecko.com/coins/images/2822/large/huobi-token-logo.png?1547036992",
		"last_updated": "2023-03-30T09:53:55.074Z",
		"low_24h": 3.63,
		"market_cap": 597292971,
		"market_cap_change_24h": 8064716,
		"market_cap_change_percentage_24h": 1.36869,
		"market_cap_rank": 80,
		"max_supply": 203980445.3,
		"name": "Huobi",
		"price_change_24h": 0.04915286,
		"price_change_percentage_24h": 1.35395,
		"roi": {
			"currency": "usd",
			"percentage": 271.66424682951344,
			"times": 2.7166424682951344
		},
		"symbol": "ht",
		"total_supply": 203980445.3,
		"total_volume": 6998525
	},
	{
		"ath": 0.192754,
		"ath_change_percentage": -78.67426,
		"ath_date": "2021-08-21T04:39:48.324Z",
		"atl": 0.00039532,
		"atl_change_percentage": 10298.27335,
		"atl_date": "2019-07-22T00:00:00.000Z",
		"circulating_supply": 13825288863.3,
		"current_price": 0.0411269,
		"fully_diluted_valuation": null,
		"high_24h": 0.04227971,
		"id": "xdce-crowd-sale",
		"image": "https://assets.coingecko.com/coins/images/2912/large/xdc-icon.png?1633700890",
		"last_updated": "2023-03-30T09:53:51.682Z",
		"low_24h": 0.04103376,
		"market_cap": 568511709,
		"market_cap_change_24h": -7557964.065136075,
		"market_cap_change_percentage_24h": -1.31199,
		"market_cap_rank": 84,
		"max_supply": null,
		"name": "XDC Network",
		"price_change_24h": -0.000460927710111615,
		"price_change_percentage_24h": -1.10832,
		"roi": {
			"currency": "eth",
			"percentage": 203.8390494554803,
			"times": 2.038390494554803
		},
		"symbol": "xdc",
		"total_supply": 37825289756.85,
		"total_volume": 5679473
	},
	{
		"ath": 0.515471,
		"ath_change_percentage": -22.36633,
		"ath_date": "2023-02-16T08:52:49.445Z",
		"atl": 0.0142795,
		"atl_change_percentage": 2702.47311,
		"atl_date": "2020-06-25T04:17:05.895Z",
		"circulating_supply": 1400001000,
		"current_price": 0.401125,
		"fully_diluted_valuation": 799241682,
		"high_24h": 0.409472,
		"id": "bitget-token",
		"image": "https://assets.coingecko.com/coins/images/11610/large/photo_2022-01-24_14-08-03.jpg?1643019457",
		"last_updated": "2023-03-30T09:53:29.333Z",
		"low_24h": 0.393176,
		"market_cap": 559469577,
		"market_cap_change_24h": -7814698.764024377,
		"market_cap_change_percentage_24h": -1.37756,
		"market_cap_rank": 85,
		"max_supply": 2000000000,
		"name": "Bitget Token",
		"price_change_24h": -0.004425244337719348,
		"price_change_percentage_24h": -1.09117,
		"roi": null,
		"symbol": "bgb",
		"total_supply": 2000000000,
		"total_volume": 10861714
	},
	{
		"ath": 0.058843,
		"ath_change_percentage": -61.25095,
		"ath_date": "2020-10-21T11:24:27.820Z",
		"atl": 0.00620705,
		"atl_change_percentage": 267.34437,
		"atl_date": "2021-03-04T08:11:37.438Z",
		"circulating_supply": 23312368308.3357,
		"current_price": 0.02280126,
		"fully_diluted_valuation": null,
		"high_24h": 0.02283871,
		"id": "compound-usd-coin",
		"image": "https://assets.coingecko.com/coins/images/9442/large/Compound_USDC.png?1567581577",
		"last_updated": "2023-03-30T09:07:00.992Z",
		"low_24h": 0.02277463,
		"market_cap": 531551480,
		"market_cap_change_24h": 75366331,
		"market_cap_change_percentage_24h": 16.521,
		"market_cap_rank": 86,
		"max_supply": null,
		"name": "cUSDC",
		"price_change_24h": 4.9985e-8,
		"price_change_percentage_24h": 0.00022,
		"roi": null,
		"symbol": "cusdc",
		"total_supply": 23312368308.3357,
		"total_volume": 8.96
	},
	{
		"ath": 97.75,
		"ath_change_percentage": -62.97973,
		"ath_date": "2021-11-21T12:39:57.508Z",
		"atl": 1.89,
		"atl_change_percentage": 1818.45147,
		"atl_date": "2020-03-13T02:22:33.711Z",
		"circulating_supply": 14187781.0507585,
		"current_price": 36.19,
		"fully_diluted_valuation": 513421132,
		"high_24h": 36.49,
		"id": "compound-ether",
		"image": "https://assets.coingecko.com/coins/images/10643/large/ceth2.JPG?1581389598",
		"last_updated": "2023-03-30T09:53:31.431Z",
		"low_24h": 35.92,
		"market_cap": 513420651,
		"market_cap_change_24h": -40989228.68701053,
		"market_cap_change_percentage_24h": -7.39331,
		"market_cap_rank": 87,
		"max_supply": null,
		"name": "cETH",
		"price_change_24h": -0.30362695073750956,
		"price_change_percentage_24h": -0.83206,
		"roi": null,
		"symbol": "ceth",
		"total_supply": 14187794.361005,
		"total_volume": 41.05
	},
	{
		"ath": 2241.37,
		"ath_change_percentage": -11.73329,
		"ath_date": "2021-05-17T19:02:29.657Z",
		"atl": 1399.64,
		"atl_change_percentage": 41.34925,
		"atl_date": "2019-11-18T03:09:35.959Z",
		"circulating_supply": 256583.817,
		"current_price": 1978.39,
		"fully_diluted_valuation": null,
		"high_24h": 1992.18,
		"id": "pax-gold",
		"image": "https://assets.coingecko.com/coins/images/9519/large/paxg.PNG?1568542565",
		"last_updated": "2023-03-30T09:53:52.146Z",
		"low_24h": 1965.08,
		"market_cap": 507593505,
		"market_cap_change_24h": -1023485.7519494891,
		"market_cap_change_percentage_24h": -0.20123,
		"market_cap_rank": 88,
		"max_supply": null,
		"name": "PAX Gold",
		"price_change_24h": -7.720218068671784,
		"price_change_percentage_24h": -0.38871,
		"roi": null,
		"symbol": "paxg",
		"total_supply": 256583.817,
		"total_volume": 12035973
	},
	{
		"ath": 0.95023,
		"ath_change_percentage": -55.95378,
		"ath_date": "2018-01-28T00:00:00.000Z",
		"atl": 0.00747159,
		"atl_change_percentage": 5501.758,
		"atl_date": "2020-03-13T02:24:16.528Z",
		"circulating_supply": 1206121857.26201,
		"current_price": 0.418429,
		"fully_diluted_valuation": 837103218,
		"high_24h": 0.448802,
		"id": "singularitynet",
		"image": "https://assets.coingecko.com/coins/images/2138/large/singularitynet.png?1548609559",
		"last_updated": "2023-03-30T09:54:00.670Z",
		"low_24h": 0.41737,
		"market_cap": 504824244,
		"market_cap_change_24h": -35683407.548169434,
		"market_cap_change_percentage_24h": -6.60183,
		"market_cap_rank": 89,
		"max_supply": 2000000000,
		"name": "SingularityNET",
		"price_change_24h": -0.029671889095225668,
		"price_change_percentage_24h": -6.6217,
		"roi": {
			"currency": "usd",
			"percentage": 318.4288106942039,
			"times": 3.184288106942039
		},
		"symbol": "agix",
		"total_supply": 1271927708.23659,
		"total_volume": 125694462
	},
	{
		"ath": 22.3,
		"ath_change_percentage": -71.81536,
		"ath_date": "2022-10-31T10:23:59.455Z",
		"atl": 0.111255,
		"atl_change_percentage": 5548.40274,
		"atl_date": "2019-04-28T00:00:00.000Z",
		"circulating_supply": 79995999.94518414,
		"current_price": 6.28,
		"fully_diluted_valuation": 627828281,
		"high_24h": 6.37,
		"id": "tokenize-xchange",
		"image": "https://assets.coingecko.com/coins/images/4984/large/TKX_-_Logo_-_RGB-15.png?1672912391",
		"last_updated": "2023-03-30T09:51:14.176Z",
		"low_24h": 6.22,
		"market_cap": 502237511,
		"market_cap_change_24h": -3375752.4848015904,
		"market_cap_change_percentage_24h": -0.66766,
		"market_cap_rank": 91,
		"max_supply": 100000000,
		"name": "Tokenize Xchange",
		"price_change_24h": -0.046943545138380394,
		"price_change_percentage_24h": -0.74216,
		"roi": {
			"currency": "usd",
			"percentage": 2061.198901214456,
			"times": 20.61198901214456
		},
		"symbol": "tkx",
		"total_supply": 100000000,
		"total_volume": 5103908
	},
	{
		"ath": 41.45,
		"ath_change_percentage": -84.57558,
		"ath_date": "2021-02-24T17:42:44.637Z",
		"atl": 0.976528,
		"atl_change_percentage": 554.63835,
		"atl_date": "2022-10-13T10:36:10.009Z",
		"circulating_supply": 76150000,
		"current_price": 6.39,
		"fully_diluted_valuation": 639365298,
		"high_24h": 7.17,
		"id": "mask-network",
		"image": "https://assets.coingecko.com/coins/images/14051/large/Mask_Network.jpg?1614050316",
		"last_updated": "2023-03-30T09:54:00.389Z",
		"low_24h": 6.38,
		"market_cap": 486876674,
		"market_cap_change_24h": -36944418.42900592,
		"market_cap_change_percentage_24h": -7.05287,
		"market_cap_rank": 93,
		"max_supply": 100000000,
		"name": "Mask Network",
		"price_change_24h": -0.48388068895057934,
		"price_change_percentage_24h": -7.03457,
		"roi": null,
		"symbol": "mask",
		"total_supply": 100000000,
		"total_volume": 337910001
	},
	{
		"ath": 2169.74,
		"ath_change_percentage": -9.13979,
		"ath_date": "2023-03-15T20:36:21.941Z",
		"atl": 1447.84,
		"atl_change_percentage": 36.16347,
		"atl_date": "2020-03-19T13:45:41.821Z",
		"circulating_supply": 246524.33,
		"current_price": 1971.48,
		"fully_diluted_valuation": 486054917,
		"high_24h": 1985.38,
		"id": "tether-gold",
		"image": "https://assets.coingecko.com/coins/images/10481/large/Tether_Gold.png?1668148656",
		"last_updated": "2023-03-30T09:53:23.944Z",
		"low_24h": 1941.24,
		"market_cap": 486054917,
		"market_cap_change_24h": -165589.12031829357,
		"market_cap_change_percentage_24h": -0.03406,
		"market_cap_rank": 94,
		"max_supply": null,
		"name": "Tether Gold",
		"price_change_24h": 2.27,
		"price_change_percentage_24h": 0.11505,
		"roi": null,
		"symbol": "xaut",
		"total_supply": 246524.33,
		"total_volume": 7154642
	},
	{
		"ath": 8.65,
		"ath_change_percentage": -93.38282,
		"ath_date": "2021-10-27T08:24:54.808Z",
		"atl": 0.37369,
		"atl_change_percentage": 53.20011,
		"atl_date": "2022-12-30T12:35:04.113Z",
		"circulating_supply": 834800083.796799,
		"current_price": 0.564334,
		"fully_diluted_valuation": 839798318,
		"high_24h": 0.568234,
		"id": "1inch",
		"image": "https://assets.coingecko.com/coins/images/13469/large/1inch-token.png?1608803028",
		"last_updated": "2023-03-30T09:53:51.931Z",
		"low_24h": 0.508746,
		"market_cap": 467375804,
		"market_cap_change_24h": 41644144,
		"market_cap_change_percentage_24h": 9.78178,
		"market_cap_rank": 95,
		"max_supply": 1500000000,
		"name": "1inch",
		"price_change_24h": 0.05428,
		"price_change_percentage_24h": 10.64193,
		"roi": null,
		"symbol": "1inch",
		"total_supply": 1500000000,
		"total_volume": 103978753
	},
	{
		"ath": 8.78,
		"ath_change_percentage": -85.57541,
		"ath_date": "2021-11-21T10:03:19.097Z",
		"atl": 0.03665669,
		"atl_change_percentage": 3356.15694,
		"atl_date": "2020-06-16T13:22:25.900Z",
		"circulating_supply": 361444954.108796,
		"current_price": 1.27,
		"fully_diluted_valuation": 672388924,
		"high_24h": 1.31,
		"id": "render-token",
		"image": "https://assets.coingecko.com/coins/images/11636/large/rndr.png?1638840934",
		"last_updated": "2023-03-30T09:54:00.061Z",
		"low_24h": 1.2,
		"market_cap": 457672736,
		"market_cap_change_24h": 14179413,
		"market_cap_change_percentage_24h": 3.19721,
		"market_cap_rank": 97,
		"max_supply": 531016083.388796,
		"name": "Render",
		"price_change_24h": 0.03865802,
		"price_change_percentage_24h": 3.1487,
		"roi": null,
		"symbol": "rndr",
		"total_supply": 531016083.388796,
		"total_volume": 51533255
	},
	{
		"ath": 3.75,
		"ath_change_percentage": -90.54237,
		"ath_date": "2021-11-10T14:59:53.164Z",
		"atl": 0.01963893,
		"atl_change_percentage": 1705.83136,
		"atl_date": "2019-12-18T13:14:41.553Z",
		"circulating_supply": 1245991468.94246,
		"current_price": 0.355376,
		"fully_diluted_valuation": 488282984,
		"high_24h": 0.374585,
		"id": "loopring",
		"image": "https://assets.coingecko.com/coins/images/913/large/LRC.png?1572852344",
		"last_updated": "2023-03-30T09:53:55.696Z",
		"low_24h": 0.353951,
		"market_cap": 442626615,
		"market_cap_change_24h": -12090718.037647843,
		"market_cap_change_percentage_24h": -2.65895,
		"market_cap_rank": 100,
		"max_supply": 1374513896,
		"name": "Loopring",
		"price_change_24h": -0.009195627144158948,
		"price_change_percentage_24h": -2.52231,
		"roi": {
			"currency": "usd",
			"percentage": 492.2931093135112,
			"times": 4.922931093135111
		},
		"symbol": "lrc",
		"total_supply": 1373873397.44246,
		"total_volume": 83085055
	},
	{
		"ath": 4814.31,
		"ath_change_percentage": -60.01817,
		"ath_date": "2021-12-01T08:03:50.749Z",
		"atl": 887.26,
		"atl_change_percentage": 116.94222,
		"atl_date": "2022-06-18T20:55:45.957Z",
		"circulating_supply": 216531.891848725,
		"current_price": 1925.17,
		"fully_diluted_valuation": null,
		"high_24h": 1951.74,
		"id": "rocket-pool-eth",
		"image": "https://assets.coingecko.com/coins/images/20764/large/reth.png?1637652366",
		"last_updated": "2023-03-30T09:53:31.124Z",
		"low_24h": 1909.45,
		"market_cap": 416903978,
		"market_cap_change_24h": -3717015.9377657175,
		"market_cap_change_percentage_24h": -0.8837,
		"market_cap_rank": 103,
		"max_supply": null,
		"name": "Rocket Pool ETH",
		"price_change_24h": -18.60476916055768,
		"price_change_percentage_24h": -0.95715,
		"roi": null,
		"symbol": "reth",
		"total_supply": 216531.891848725,
		"total_volume": 2659438
	},
	{
		"ath": 4.07,
		"ath_change_percentage": -81.74175,
		"ath_date": "2021-05-12T14:37:47.535Z",
		"atl": 0.04515276,
		"atl_change_percentage": 1544.94952,
		"atl_date": "2018-09-13T00:00:00.000Z",
		"circulating_supply": 560000010.0064,
		"current_price": 0.742043,
		"fully_diluted_valuation": 741516908,
		"high_24h": 0.75864,
		"id": "nexo",
		"image": "https://assets.coingecko.com/coins/images/3695/large/nexo.png?1548086057",
		"last_updated": "2023-03-30T09:53:59.457Z",
		"low_24h": 0.727255,
		"market_cap": 415249476,
		"market_cap_change_24h": 8945050,
		"market_cap_change_percentage_24h": 2.20156,
		"market_cap_rank": 104,
		"max_supply": 1000000000,
		"name": "NEXO",
		"price_change_24h": 0.01478799,
		"price_change_percentage_24h": 2.0334,
		"roi": {
			"currency": "usd",
			"percentage": 642.0431014541236,
			"times": 6.420431014541236
		},
		"symbol": "nexo",
		"total_supply": 1000000000,
		"total_volume": 9675622
	},
	{
		"ath": 60.09,
		"ath_change_percentage": -91.02284,
		"ath_date": "2022-01-01T18:04:03.030Z",
		"atl": 1.9,
		"atl_change_percentage": 183.47398,
		"atl_date": "2021-07-20T13:17:29.183Z",
		"circulating_supply": 75963467.88313277,
		"current_price": 5.39,
		"fully_diluted_valuation": 538947312,
		"high_24h": 5.48,
		"id": "convex-finance",
		"image": "https://assets.coingecko.com/coins/images/15585/large/convex.png?1621256328",
		"last_updated": "2023-03-30T09:53:57.500Z",
		"low_24h": 5.31,
		"market_cap": 409403068,
		"market_cap_change_24h": 5018319,
		"market_cap_change_percentage_24h": 1.24098,
		"market_cap_rank": 107,
		"max_supply": 100000000,
		"name": "Convex Finance",
		"price_change_24h": 0.04939938,
		"price_change_percentage_24h": 0.92466,
		"roi": null,
		"symbol": "cvx",
		"total_supply": 97790847.7977506,
		"total_volume": 4958805
	},
	{
		"ath": 3.3,
		"ath_change_percentage": -69.72177,
		"ath_date": "2018-10-11T17:36:21.529Z",
		"atl": 0.78261,
		"atl_change_percentage": 27.82252,
		"atl_date": "2018-09-29T00:00:00.000Z",
		"circulating_supply": 391759067.13,
		"current_price": 1,
		"fully_diluted_valuation": 392239337,
		"high_24h": 1.008,
		"id": "gemini-dollar",
		"image": "https://assets.coingecko.com/coins/images/5992/large/gemini-dollar-gusd.png?1536745278",
		"last_updated": "2023-03-30T09:53:59.052Z",
		"low_24h": 0.996614,
		"market_cap": 392239337,
		"market_cap_change_24h": -498241.52379369736,
		"market_cap_change_percentage_24h": -0.12686,
		"market_cap_rank": 109,
		"max_supply": null,
		"name": "Gemini Dollar",
		"price_change_24h": -0.000925263014980748,
		"price_change_percentage_24h": -0.09242,
		"roi": {
			"currency": "usd",
			"percentage": 0.0268267019586,
			"times": 0.000268267019586
		},
		"symbol": "gusd",
		"total_supply": 391759067.13,
		"total_volume": 535112
	},
	{
		"ath": 4.82,
		"ath_change_percentage": -91.8802,
		"ath_date": "2021-11-25T09:53:41.955Z",
		"atl": 0.01865964,
		"atl_change_percentage": 1997.14798,
		"atl_date": "2017-11-12T00:00:00.000Z",
		"circulating_supply": 1000000000,
		"current_price": 0.392013,
		"fully_diluted_valuation": 392070501,
		"high_24h": 0.407087,
		"id": "enjincoin",
		"image": "https://assets.coingecko.com/coins/images/1102/large/enjin-coin-logo.png?1547035078",
		"last_updated": "2023-03-30T09:53:56.670Z",
		"low_24h": 0.390885,
		"market_cap": 392070501,
		"market_cap_change_24h": -1554794.8855032325,
		"market_cap_change_percentage_24h": -0.39499,
		"market_cap_rank": 111,
		"max_supply": 1000000000,
		"name": "Enjin Coin",
		"price_change_24h": -0.000650865998833572,
		"price_change_percentage_24h": -0.16576,
		"roi": null,
		"symbol": "enj",
		"total_supply": 1000000000,
		"total_volume": 33267488
	},
	{
		"ath": 0.03159087,
		"ath_change_percentage": -29.74498,
		"ath_date": "2020-10-12T21:29:00.007Z",
		"atl": 0.00728854,
		"atl_change_percentage": 204.50758,
		"atl_date": "2020-03-18T04:29:40.819Z",
		"circulating_supply": 17647092934.5876,
		"current_price": 0.02219417,
		"fully_diluted_valuation": 391662566,
		"high_24h": 0.02224061,
		"id": "cdai",
		"image": "https://assets.coingecko.com/coins/images/9281/large/cDAI.png?1576467585",
		"last_updated": "2023-03-30T09:07:00.966Z",
		"low_24h": 0.02216003,
		"market_cap": 391662549,
		"market_cap_change_24h": -10042863.417278588,
		"market_cap_change_percentage_24h": -2.50006,
		"market_cap_rank": 110,
		"max_supply": null,
		"name": "cDAI",
		"price_change_24h": 0.00000263,
		"price_change_percentage_24h": 0.01184,
		"roi": null,
		"symbol": "cdai",
		"total_supply": 17647093729.9201,
		"total_volume": 578.95
	},
	{
		"ath": 1.17,
		"ath_change_percentage": -68.33169,
		"ath_date": "2021-09-08T02:24:24.858Z",
		"atl": 0.00816959,
		"atl_change_percentage": 4443.08115,
		"atl_date": "2020-03-13T02:24:18.347Z",
		"circulating_supply": 1043462805,
		"current_price": 0.370577,
		"fully_diluted_valuation": 426808331,
		"high_24h": 0.391408,
		"id": "fetch-ai",
		"image": "https://assets.coingecko.com/coins/images/5681/large/Fetch.jpg?1572098136",
		"last_updated": "2023-03-30T09:53:57.486Z",
		"low_24h": 0.362234,
		"market_cap": 386261539,
		"market_cap_change_24h": 634666,
		"market_cap_change_percentage_24h": 0.16458,
		"market_cap_rank": 113,
		"max_supply": 1152997575,
		"name": "Fetch.ai",
		"price_change_24h": 0.00155023,
		"price_change_percentage_24h": 0.42008,
		"roi": {
			"currency": "usd",
			"percentage": 327.4245624939855,
			"times": 3.2742456249398546
		},
		"symbol": "fet",
		"total_supply": 1152997575,
		"total_volume": 119232333
	},
	{
		"ath": 27.86,
		"ath_change_percentage": -91.18505,
		"ath_date": "2021-09-30T01:23:43.570Z",
		"atl": 1.011,
		"atl_change_percentage": 143.0118,
		"atl_date": "2022-06-18T20:55:50.603Z",
		"circulating_supply": 155231046.27094412,
		"current_price": 2.46,
		"fully_diluted_valuation": 2458433018,
		"high_24h": 2.6,
		"id": "dydx",
		"image": "https://assets.coingecko.com/coins/images/17500/large/hjnIm9bV.jpg?1628009360",
		"last_updated": "2023-03-30T09:53:55.331Z",
		"low_24h": 2.45,
		"market_cap": 381625130,
		"market_cap_change_24h": -17786961.21700746,
		"market_cap_change_percentage_24h": -4.45329,
		"market_cap_rank": 116,
		"max_supply": 1000000000,
		"name": "dYdX",
		"price_change_24h": -0.12055826491319799,
		"price_change_percentage_24h": -4.67189,
		"roi": null,
		"symbol": "dydx",
		"total_supply": 1000000000,
		"total_volume": 166029033
	},
	{
		"ath": 9.21,
		"ath_change_percentage": -74.19961,
		"ath_date": "2022-03-23T09:11:07.549Z",
		"atl": 0.631269,
		"atl_change_percentage": 276.60713,
		"atl_date": "2020-12-13T14:22:21.597Z",
		"circulating_supply": 162061501,
		"current_price": 2.35,
		"fully_diluted_valuation": 469190008,
		"high_24h": 2.39,
		"id": "btse-token",
		"image": "https://assets.coingecko.com/coins/images/10807/large/BTSE_logo_Square.jpeg?1583965964",
		"last_updated": "2023-03-30T09:53:03.402Z",
		"low_24h": 2.33,
		"market_cap": 380188185,
		"market_cap_change_24h": -5164329.114575207,
		"market_cap_change_percentage_24h": -1.34016,
		"market_cap_rank": 115,
		"max_supply": 200000000,
		"name": "BTSE Token",
		"price_change_24h": -0.03225766817987674,
		"price_change_percentage_24h": -1.3565,
		"roi": {
			"currency": "usd",
			"percentage": 17.28727023175305,
			"times": 0.1728727023175305
		},
		"symbol": "btse",
		"total_supply": 200000000,
		"total_volume": 1051989
	},
	{
		"ath": 1.9,
		"ath_change_percentage": -86.87623,
		"ath_date": "2021-11-28T00:23:51.354Z",
		"atl": 0.072394,
		"atl_change_percentage": 244.53863,
		"atl_date": "2017-07-16T00:00:00.000Z",
		"circulating_supply": 1485963548.4163349,
		"current_price": 0.250633,
		"fully_diluted_valuation": 374969957,
		"high_24h": 0.258315,
		"id": "basic-attention-token",
		"image": "https://assets.coingecko.com/coins/images/677/large/basic-attention-token.png?1547034427",
		"last_updated": "2023-03-30T09:53:52.728Z",
		"low_24h": 0.249252,
		"market_cap": 371461125,
		"market_cap_change_24h": -5303635.454416156,
		"market_cap_change_percentage_24h": -1.40768,
		"market_cap_rank": 118,
		"max_supply": 1500000000,
		"name": "Basic Attention",
		"price_change_24h": -0.002955145457772146,
		"price_change_percentage_24h": -1.16533,
		"roi": {
			"currency": "eth",
			"percentage": -10.884417110283968,
			"times": -0.10884417110283968
		},
		"symbol": "bat",
		"total_supply": 1500000000,
		"total_volume": 48656633
	},
	{
		"ath": 1.78,
		"ath_change_percentage": -88.25323,
		"ath_date": "2021-11-15T13:44:18.437Z",
		"atl": 0.02211546,
		"atl_change_percentage": 844.55161,
		"atl_date": "2021-01-04T10:19:13.803Z",
		"circulating_supply": 1676815272.54284,
		"current_price": 0.209506,
		"fully_diluted_valuation": 471375348,
		"high_24h": 0.218159,
		"id": "woo-network",
		"image": "https://assets.coingecko.com/coins/images/12921/large/w2UiemF__400x400.jpg?1603670367",
		"last_updated": "2023-03-30T09:53:54.470Z",
		"low_24h": 0.199443,
		"market_cap": 351190221,
		"market_cap_change_24h": 11181221,
		"market_cap_change_percentage_24h": 3.28851,
		"market_cap_rank": 122,
		"max_supply": 2250658857.90186,
		"name": "WOO Network",
		"price_change_24h": 0.00673276,
		"price_change_percentage_24h": 3.32033,
		"roi": null,
		"symbol": "woo",
		"total_supply": 2250658857.90186,
		"total_volume": 25011369
	},
	{
		"ath": 83.4,
		"ath_change_percentage": -84.13583,
		"ath_date": "2021-11-11T02:20:01.099Z",
		"atl": 7.45,
		"atl_change_percentage": 77.54059,
		"atl_date": "2022-06-14T02:00:36.378Z",
		"circulating_supply": 25783233.34309683,
		"current_price": 13.24,
		"fully_diluted_valuation": 1323989059,
		"high_24h": 13.77,
		"id": "ethereum-name-service",
		"image": "https://assets.coingecko.com/coins/images/19785/large/acatxTm8_400x400.jpg?1635850140",
		"last_updated": "2023-03-30T09:53:52.853Z",
		"low_24h": 13.2,
		"market_cap": 341367189,
		"market_cap_change_24h": -5421123.896421671,
		"market_cap_change_percentage_24h": -1.56324,
		"market_cap_rank": 124,
		"max_supply": 100000000,
		"name": "Ethereum Name Service",
		"price_change_24h": -0.20160831852960115,
		"price_change_percentage_24h": -1.49966,
		"roi": null,
		"symbol": "ens",
		"total_supply": 100000000,
		"total_volume": 30079136
	},
	{
		"ath": 24.89,
		"ath_change_percentage": -82.98534,
		"ath_date": "2021-04-30T00:33:02.969Z",
		"atl": 0.657401,
		"atl_change_percentage": 544.19257,
		"atl_date": "2020-11-03T16:19:30.576Z",
		"circulating_supply": 80005555.33,
		"current_price": 4.25,
		"fully_diluted_valuation": 425193659,
		"high_24h": 4.44,
		"id": "injective-protocol",
		"image": "https://assets.coingecko.com/coins/images/12882/large/Secondary_Symbol.png?1628233237",
		"last_updated": "2023-03-30T09:53:59.412Z",
		"low_24h": 4.22,
		"market_cap": 340178548,
		"market_cap_change_24h": -7642862.207621813,
		"market_cap_change_percentage_24h": -2.19735,
		"market_cap_rank": 125,
		"max_supply": 100000000,
		"name": "Injective",
		"price_change_24h": -0.08779209567300585,
		"price_change_percentage_24h": -2.02312,
		"roi": null,
		"symbol": "inj",
		"total_supply": 100000000,
		"total_volume": 44013074
	},
	{
		"ath": 185.97,
		"ath_change_percentage": -73.19811,
		"ath_date": "2021-11-10T15:14:14.418Z",
		"atl": 6.96,
		"atl_change_percentage": 615.85685,
		"atl_date": "2020-07-22T19:54:06.406Z",
		"circulating_supply": 6760774.64443073,
		"current_price": 49.84,
		"fully_diluted_valuation": 336986953,
		"high_24h": 50.28,
		"id": "nxm",
		"image": "https://assets.coingecko.com/coins/images/11810/large/NXMmain.png?1674799570",
		"last_updated": "2023-03-30T09:07:01.877Z",
		"low_24h": 49.5,
		"market_cap": 336986953,
		"market_cap_change_24h": -2939454.3982006907,
		"market_cap_change_percentage_24h": -0.86473,
		"market_cap_rank": 126,
		"max_supply": 6760774.64443073,
		"name": "Nexus Mutual",
		"price_change_24h": -0.43477806178157863,
		"price_change_percentage_24h": -0.86473,
		"roi": null,
		"symbol": "nxm",
		"total_supply": 6760774.64443073,
		"total_volume": 13520.53
	},
	{
		"ath": 6.345e-9,
		"ath_change_percentage": -66.40125,
		"ath_date": "2022-01-16T20:24:43.758Z",
		"atl": 9.4771e-11,
		"atl_change_percentage": 2149.37513,
		"atl_date": "2021-06-09T02:48:21.787Z",
		"circulating_supply": 156124856092293500,
		"current_price": 2.169e-9,
		"fully_diluted_valuation": 896088452,
		"high_24h": 2.22e-9,
		"id": "baby-doge-coin",
		"image": "https://assets.coingecko.com/coins/images/16125/large/babydoge.jpg?1676303229",
		"last_updated": "2023-03-30T09:53:51.067Z",
		"low_24h": 2.104e-9,
		"market_cap": 333099240,
		"market_cap_change_24h": 2432065,
		"market_cap_change_percentage_24h": 0.7355,
		"market_cap_rank": 127,
		"max_supply": 420000000000000000,
		"name": "Baby Doge Coin",
		"price_change_24h": 4.5441e-11,
		"price_change_percentage_24h": 2.1403,
		"roi": null,
		"symbol": "babydoge",
		"total_supply": 420000000000000000,
		"total_volume": 3972040
	},
	{
		"ath": 0.00033651,
		"ath_change_percentage": -89.95883,
		"ath_date": "2021-11-04T06:58:35.285Z",
		"atl": 8.428e-8,
		"atl_change_percentage": 39991.67812,
		"atl_date": "2021-07-06T01:11:20.438Z",
		"circulating_supply": 9784148354849.71,
		"current_price": 0.00003359,
		"fully_diluted_valuation": null,
		"high_24h": 0.00003527,
		"id": "floki",
		"image": "https://assets.coingecko.com/coins/images/16746/large/PNG_image.png?1643184642",
		"last_updated": "2023-03-30T09:53:47.550Z",
		"low_24h": 0.00003358,
		"market_cap": 330584203,
		"market_cap_change_24h": -13563569.783823013,
		"market_cap_change_percentage_24h": -3.94121,
		"market_cap_rank": 129,
		"max_supply": null,
		"name": "FLOKI",
		"price_change_24h": -0.00000155732565861,
		"price_change_percentage_24h": -4.43069,
		"roi": null,
		"symbol": "floki",
		"total_supply": 10000000000000,
		"total_volume": 21926008
	},
	{
		"ath": 0.03126682,
		"ath_change_percentage": -94.07491,
		"ath_date": "2021-04-05T16:04:52.608Z",
		"atl": 0.0002202,
		"atl_change_percentage": 741.32409,
		"atl_date": "2020-03-13T02:23:01.612Z",
		"circulating_supply": 177619433541.141,
		"current_price": 0.00185445,
		"fully_diluted_valuation": null,
		"high_24h": 0.0018883,
		"id": "holotoken",
		"image": "https://assets.coingecko.com/coins/images/3348/large/Holologo_Profile.png?1547037966",
		"last_updated": "2023-03-30T09:53:57.052Z",
		"low_24h": 0.00181358,
		"market_cap": 329325922,
		"market_cap_change_24h": -209634.49109315872,
		"market_cap_change_percentage_24h": -0.06362,
		"market_cap_rank": 128,
		"max_supply": null,
		"name": "Holo",
		"price_change_24h": -0.000001422864432581,
		"price_change_percentage_24h": -0.07667,
		"roi": {
			"currency": "eth",
			"percentage": 354.42582925719444,
			"times": 3.544258292571944
		},
		"symbol": "hot",
		"total_supply": 177619433541.141,
		"total_volume": 23672455
	},
	{
		"ath": 0.824837,
		"ath_change_percentage": -95.00313,
		"ath_date": "2021-11-26T01:03:48.731Z",
		"atl": 0.00013475,
		"atl_change_percentage": 30487.14248,
		"atl_date": "2020-12-28T08:46:48.367Z",
		"circulating_supply": 7542496572.319239,
		"current_price": 0.04122985,
		"fully_diluted_valuation": 2060815585,
		"high_24h": 0.04266675,
		"id": "gala",
		"image": "https://assets.coingecko.com/coins/images/12493/large/GALA-COINGECKO.png?1600233435",
		"last_updated": "2023-03-30T09:53:52.313Z",
		"low_24h": 0.04032536,
		"market_cap": 310873890,
		"market_cap_change_24h": -1367731.1912332177,
		"market_cap_change_percentage_24h": -0.43804,
		"market_cap_rank": 135,
		"max_supply": 50000000000,
		"name": "GALA",
		"price_change_24h": -0.000184227196551236,
		"price_change_percentage_24h": -0.44484,
		"roi": null,
		"symbol": "gala",
		"total_supply": 39239193603.0149,
		"total_volume": 232072645
	},
	{
		"ath": 910.54,
		"ath_change_percentage": -95.34296,
		"ath_date": "2021-05-12T02:29:08.794Z",
		"atl": 26.41,
		"atl_change_percentage": 60.56038,
		"atl_date": "2022-06-18T20:54:18.261Z",
		"circulating_supply": 6856085.76329154,
		"current_price": 42.42,
		"fully_diluted_valuation": 424258988,
		"high_24h": 44.12,
		"id": "compound-governance-token",
		"image": "https://assets.coingecko.com/coins/images/10775/large/COMP.png?1592625425",
		"last_updated": "2023-03-30T09:53:53.947Z",
		"low_24h": 42.38,
		"market_cap": 290875601,
		"market_cap_change_24h": -6297939.4064356685,
		"market_cap_change_percentage_24h": -2.11928,
		"market_cap_rank": 139,
		"max_supply": 10000000,
		"name": "Compound",
		"price_change_24h": -0.8361286594062705,
		"price_change_percentage_24h": -1.93284,
		"roi": null,
		"symbol": "comp",
		"total_supply": 10000000,
		"total_volume": 21484538
	},
	{
		"ath": 6.32,
		"ath_change_percentage": -78.4684,
		"ath_date": "2022-02-19T16:24:53.615Z",
		"atl": 0.01999252,
		"atl_change_percentage": 6710.40002,
		"atl_date": "2021-10-07T01:57:51.729Z",
		"circulating_supply": 212598597.988376,
		"current_price": 1.36,
		"fully_diluted_valuation": 473633070,
		"high_24h": 1.46,
		"id": "magic",
		"image": "https://assets.coingecko.com/coins/images/18623/large/magic.png?1656052146",
		"last_updated": "2023-03-30T09:53:55.732Z",
		"low_24h": 1.36,
		"market_cap": 289587778,
		"market_cap_change_24h": -18973367.05218911,
		"market_cap_change_percentage_24h": -6.14898,
		"market_cap_rank": 140,
		"max_supply": 347714007,
		"name": "Magic",
		"price_change_24h": -0.08852245197183906,
		"price_change_percentage_24h": -6.10279,
		"roi": null,
		"symbol": "magic",
		"total_supply": 339645510.317976,
		"total_volume": 74603398
	},
	{
		"ath": 644.2,
		"ath_change_percentage": -82.65834,
		"ath_date": "2021-11-08T17:33:29.302Z",
		"atl": 6.88,
		"atl_change_percentage": 1522.8027,
		"atl_date": "2020-03-13T02:24:11.825Z",
		"circulating_supply": 2589589,
		"current_price": 111.66,
		"fully_diluted_valuation": 334902067,
		"high_24h": 113.47,
		"id": "gnosis",
		"image": "https://assets.coingecko.com/coins/images/662/large/logo_square_simple_300px.png?1609402668",
		"last_updated": "2023-03-30T09:53:57.873Z",
		"low_24h": 111.61,
		"market_cap": 289086237,
		"market_cap_change_24h": -3912391.1056096554,
		"market_cap_change_percentage_24h": -1.33529,
		"market_cap_rank": 141,
		"max_supply": 3000000,
		"name": "Gnosis",
		"price_change_24h": -1.528162972841642,
		"price_change_percentage_24h": -1.35012,
		"roi": null,
		"symbol": "gno",
		"total_supply": 3000000,
		"total_volume": 2209527
	},
	{
		"ath": 90787,
		"ath_change_percentage": -90.29322,
		"ath_date": "2021-05-12T00:29:37.713Z",
		"atl": 31.65,
		"atl_change_percentage": 27747.83447,
		"atl_date": "2020-07-18T12:26:27.150Z",
		"circulating_supply": 32777.496366381085,
		"current_price": 8802.01,
		"fully_diluted_valuation": 322572906,
		"high_24h": 8996.75,
		"id": "yearn-finance",
		"image": "https://assets.coingecko.com/coins/images/11849/large/yearn-finance-yfi.png?1676174746",
		"last_updated": "2023-03-30T09:53:54.259Z",
		"low_24h": 8698.13,
		"market_cap": 288363395,
		"market_cap_change_24h": 588693,
		"market_cap_change_percentage_24h": 0.20457,
		"market_cap_rank": 142,
		"max_supply": 36666,
		"name": "yearn.finance",
		"price_change_24h": 25.23,
		"price_change_percentage_24h": 0.28751,
		"roi": null,
		"symbol": "yfi",
		"total_supply": 36666,
		"total_volume": 59996985
	},
	{
		"ath": 1415.26,
		"ath_change_percentage": -99.26826,
		"ath_date": "2021-04-25T00:00:00.000Z",
		"atl": 7.54,
		"atl_change_percentage": 37.28291,
		"atl_date": "2022-11-26T16:36:26.296Z",
		"circulating_supply": 27766805.309068747,
		"current_price": 10.34,
		"fully_diluted_valuation": 290829948,
		"high_24h": 10.4,
		"id": "olympus",
		"image": "https://assets.coingecko.com/coins/images/14483/large/token_OHM_%281%29.png?1628311611",
		"last_updated": "2023-03-30T09:53:40.965Z",
		"low_24h": 10.27,
		"market_cap": 287202642,
		"market_cap_change_24h": -1136619.0523680449,
		"market_cap_change_percentage_24h": -0.3942,
		"market_cap_rank": 144,
		"max_supply": 28117493.9684171,
		"name": "Olympus",
		"price_change_24h": -0.03584117497034889,
		"price_change_percentage_24h": -0.34534,
		"roi": null,
		"symbol": "ohm",
		"total_supply": 28117493.9684171,
		"total_volume": 822774
	},
	{
		"ath": 11444.33,
		"ath_change_percentage": -30.70343,
		"ath_date": "2023-02-17T08:10:37.065Z",
		"atl": 18.04,
		"atl_change_percentage": 43872.73281,
		"atl_date": "2021-01-26T16:14:36.262Z",
		"circulating_supply": 35833.0003763344,
		"current_price": 7930.53,
		"fully_diluted_valuation": 284174530,
		"high_24h": null,
		"id": "gains-farm",
		"image": "https://assets.coingecko.com/coins/images/13703/large/gfarm_v2.png?1611035398",
		"last_updated": "2023-03-26T07:39:19.460Z",
		"low_24h": null,
		"market_cap": 284174530,
		"market_cap_change_24h": null,
		"market_cap_change_percentage_24h": null,
		"market_cap_rank": 145,
		"max_supply": 35833.0003763344,
		"name": "Gains Farm",
		"price_change_24h": null,
		"price_change_percentage_24h": null,
		"roi": null,
		"symbol": "gfarm2",
		"total_supply": 35833.0003763344,
		"total_volume": 847.25
	},
	{
		"ath": 7.56,
		"ath_change_percentage": -62.19447,
		"ath_date": "2021-12-22T02:44:42.437Z",
		"atl": 0.00047299,
		"atl_change_percentage": 604467.28848,
		"atl_date": "2020-08-04T11:18:39.614Z",
		"circulating_supply": 98664982.8583514,
		"current_price": 2.86,
		"fully_diluted_valuation": 282357547,
		"high_24h": 2.95,
		"id": "flex-coin",
		"image": "https://assets.coingecko.com/coins/images/9108/large/coinflex_logo.png?1628750583",
		"last_updated": "2023-03-30T09:53:34.134Z",
		"low_24h": 2.77,
		"market_cap": 282155130,
		"market_cap_change_24h": 5659795,
		"market_cap_change_percentage_24h": 2.04698,
		"market_cap_rank": 146,
		"max_supply": 98735764.894,
		"name": "FLEX Coin",
		"price_change_24h": 0.04203,
		"price_change_percentage_24h": 1.49206,
		"roi": null,
		"symbol": "flex",
		"total_supply": 98735764.894,
		"total_volume": 1402763
	},
	{
		"ath": 4.95,
		"ath_change_percentage": -94.27916,
		"ath_date": "2021-03-27T15:45:35.137Z",
		"atl": 0.0437371,
		"atl_change_percentage": 548.0893,
		"atl_date": "2020-10-23T14:56:23.999Z",
		"circulating_supply": 990636746,
		"current_price": 0.283514,
		"fully_diluted_valuation": 326961003,
		"high_24h": 0.294953,
		"id": "audius",
		"image": "https://assets.coingecko.com/coins/images/12913/large/AudiusCoinLogo_2x.png?1603425727",
		"last_updated": "2023-03-30T09:53:56.541Z",
		"low_24h": 0.282729,
		"market_cap": 280742042,
		"market_cap_change_24h": -5983770.270938933,
		"market_cap_change_percentage_24h": -2.08693,
		"market_cap_rank": 147,
		"max_supply": 1153726677.79445,
		"name": "Audius",
		"price_change_24h": -0.006000888466526911,
		"price_change_percentage_24h": -2.07274,
		"roi": null,
		"symbol": "audio",
		"total_supply": 1153726677.79445,
		"total_volume": 19282891
	},
	{
		"ath": 74.45,
		"ath_change_percentage": -90.76335,
		"ath_date": "2021-05-04T13:35:02.939Z",
		"atl": 3.66,
		"atl_change_percentage": 88.10697,
		"atl_date": "2022-06-18T21:00:00.231Z",
		"circulating_supply": 40280954.4189348,
		"current_price": 6.88,
		"fully_diluted_valuation": 661204347,
		"high_24h": 7.11,
		"id": "balancer",
		"image": "https://assets.coingecko.com/coins/images/11683/large/Balancer.png?1592792958",
		"last_updated": "2023-03-30T09:53:58.339Z",
		"low_24h": 6.86,
		"market_cap": 277002050,
		"market_cap_change_24h": -3341876.908257127,
		"market_cap_change_percentage_24h": -1.19206,
		"market_cap_rank": 151,
		"max_supply": 96150704,
		"name": "Balancer",
		"price_change_24h": -0.09004645291081825,
		"price_change_percentage_24h": -1.29229,
		"roi": null,
		"symbol": "bal",
		"total_supply": 56257062.3800357,
		"total_volume": 8168579
	},
	{
		"ath": 5.79,
		"ath_change_percentage": -91.51917,
		"ath_date": "2021-05-03T15:29:39.372Z",
		"atl": 0.161303,
		"atl_change_percentage": 204.41903,
		"atl_date": "2020-03-18T13:24:48.021Z",
		"circulating_supply": 559501761.646367,
		"current_price": 0.492328,
		"fully_diluted_valuation": 274301946,
		"high_24h": 0.578633,
		"id": "swipe",
		"image": "https://assets.coingecko.com/coins/images/9368/large/swipe.png?1566792311",
		"last_updated": "2023-03-30T09:54:01.180Z",
		"low_24h": 0.326315,
		"market_cap": 274301701,
		"market_cap_change_24h": 91261570,
		"market_cap_change_percentage_24h": 49.85878,
		"market_cap_rank": 152,
		"max_supply": null,
		"name": "SXP",
		"price_change_24h": 0.16003,
		"price_change_percentage_24h": 48.15839,
		"roi": null,
		"symbol": "sxp",
		"total_supply": 559502260.552969,
		"total_volume": 1764796699
	},
	{
		"ath": 1.16,
		"ath_change_percentage": -12.73581,
		"ath_date": "2021-04-05T14:47:52.665Z",
		"atl": 0.896722,
		"atl_change_percentage": 12.72194,
		"atl_date": "2022-01-27T09:42:06.510Z",
		"circulating_supply": 268212780.267609,
		"current_price": 1.011,
		"fully_diluted_valuation": null,
		"high_24h": 1.016,
		"id": "liquity-usd",
		"image": "https://assets.coingecko.com/coins/images/14666/large/Group_3.png?1617631327",
		"last_updated": "2023-03-30T09:53:59.853Z",
		"low_24h": 1.001,
		"market_cap": 271226268,
		"market_cap_change_24h": 21187,
		"market_cap_change_percentage_24h": 0.00781,
		"market_cap_rank": 154,
		"max_supply": null,
		"name": "Liquity USD",
		"price_change_24h": -0.003161899968019189,
		"price_change_percentage_24h": -0.31189,
		"roi": null,
		"symbol": "lusd",
		"total_supply": 268221020.273351,
		"total_volume": 6533178
	},
	{
		"ath": 0.213513,
		"ath_change_percentage": -84.85125,
		"ath_date": "2021-04-16T19:44:04.474Z",
		"atl": 0.00070728,
		"atl_change_percentage": 4473.07892,
		"atl_date": "2020-03-13T02:24:03.563Z",
		"circulating_supply": 8162899377.791667,
		"current_price": 0.03237933,
		"fully_diluted_valuation": 323866996,
		"high_24h": 0.03376526,
		"id": "ankr",
		"image": "https://assets.coingecko.com/coins/images/4324/large/U85xTl2.png?1608111978",
		"last_updated": "2023-03-30T09:53:57.015Z",
		"low_24h": 0.03233741,
		"market_cap": 264369370,
		"market_cap_change_24h": -3644460.7180522084,
		"market_cap_change_percentage_24h": -1.3598,
		"market_cap_rank": 155,
		"max_supply": 10000000000,
		"name": "Ankr Network",
		"price_change_24h": -0.000476395857137851,
		"price_change_percentage_24h": -1.44996,
		"roi": {
			"currency": "usd",
			"percentage": 390.59598265828,
			"times": 3.9059598265828
		},
		"symbol": "ankr",
		"total_supply": 10000000000,
		"total_volume": 36904278
	},
	{
		"ath": 49.52,
		"ath_change_percentage": -25.4808,
		"ath_date": "2023-02-27T23:15:10.196Z",
		"atl": 3.67,
		"atl_change_percentage": 905.20103,
		"atl_date": "2022-06-18T20:56:57.599Z",
		"circulating_supply": 7085672.647228521,
		"current_price": 36.95,
		"fully_diluted_valuation": 409310337,
		"high_24h": 38.45,
		"id": "ssv-network",
		"image": "https://assets.coingecko.com/coins/images/19155/large/ssv.png?1638181902",
		"last_updated": "2023-03-30T09:53:54.690Z",
		"low_24h": 36.47,
		"market_cap": 261828368,
		"market_cap_change_24h": -8681802.343038708,
		"market_cap_change_percentage_24h": -3.20942,
		"market_cap_rank": 157,
		"max_supply": null,
		"name": "SSV Network",
		"price_change_24h": -1.1958024451498943,
		"price_change_percentage_24h": -3.13508,
		"roi": null,
		"symbol": "ssv",
		"total_supply": 11076871,
		"total_volume": 37887634
	},
	{
		"ath": 166135,
		"ath_change_percentage": -82.73527,
		"ath_date": "2022-04-21T18:59:43.859Z",
		"atl": 10704.55,
		"atl_change_percentage": 167.94889,
		"atl_date": "2023-03-10T01:30:46.660Z",
		"circulating_supply": 8969.497004742,
		"current_price": 28299,
		"fully_diluted_valuation": 253765695,
		"high_24h": 28987,
		"id": "huobi-btc",
		"image": "https://assets.coingecko.com/coins/images/12407/large/Unknown-5.png?1599624896",
		"last_updated": "2023-03-30T09:53:54.539Z",
		"low_24h": 28110,
		"market_cap": 253765695,
		"market_cap_change_24h": -130193.50502347946,
		"market_cap_change_percentage_24h": -0.05128,
		"market_cap_rank": 158,
		"max_supply": 8969.497004742,
		"name": "Huobi BTC",
		"price_change_24h": 31.91,
		"price_change_percentage_24h": 0.11287,
		"roi": null,
		"symbol": "hbtc",
		"total_supply": 8969.497004742,
		"total_volume": 52305
	},
	{
		"ath": 15.5,
		"ath_change_percentage": -93.02851,
		"ath_date": "2021-07-07T02:52:33.198Z",
		"atl": 0,
		"atl_change_percentage": 1.216455369355817e+37,
		"atl_date": "2021-08-12T23:02:53.007Z",
		"circulating_supply": 229923445.59824258,
		"current_price": 1.083,
		"fully_diluted_valuation": 270433734,
		"high_24h": 1.095,
		"id": "bone-shibaswap",
		"image": "https://assets.coingecko.com/coins/images/16916/large/bone_icon.png?1625625505",
		"last_updated": "2023-03-30T09:53:52.495Z",
		"low_24h": 1.073,
		"market_cap": 248716224,
		"market_cap_change_24h": -3622758.1268381476,
		"market_cap_change_percentage_24h": -1.43567,
		"market_cap_rank": 160,
		"max_supply": 250000000,
		"name": "Bone ShibaSwap",
		"price_change_24h": -0.012099291268776515,
		"price_change_percentage_24h": -1.10536,
		"roi": null,
		"symbol": "bone",
		"total_supply": 230003022.824847,
		"total_volume": 4076390
	},
	{
		"ath": 4.11,
		"ath_change_percentage": -90.61825,
		"ath_date": "2022-04-28T03:29:53.820Z",
		"atl": 0.100826,
		"atl_change_percentage": 282.18437,
		"atl_date": "2022-03-11T06:04:31.100Z",
		"circulating_supply": 634300284.899387,
		"current_price": 0.385614,
		"fully_diluted_valuation": 2311588577,
		"high_24h": 0.407208,
		"id": "stepn",
		"image": "https://assets.coingecko.com/coins/images/23597/large/gmt.png?1644658792",
		"last_updated": "2023-03-30T09:53:58.916Z",
		"low_24h": 0.383646,
		"market_cap": 244373549,
		"market_cap_change_24h": -4039992.042337388,
		"market_cap_change_percentage_24h": -1.62632,
		"market_cap_rank": 161,
		"max_supply": 6000000000,
		"name": "STEPN",
		"price_change_24h": -0.006605774172633805,
		"price_change_percentage_24h": -1.6842,
		"roi": null,
		"symbol": "gmt",
		"total_supply": 5548666954.89939,
		"total_volume": 69933175
	},
	{
		"ath": 0.502216,
		"ath_change_percentage": -27.99365,
		"ath_date": "2023-03-21T14:15:03.845Z",
		"atl": 0.00164788,
		"atl_change_percentage": 21844.96019,
		"atl_date": "2020-03-13T02:24:15.284Z",
		"circulating_supply": 674579184.17,
		"current_price": 0.361513,
		"fully_diluted_valuation": null,
		"high_24h": 0.373474,
		"id": "blox",
		"image": "https://assets.coingecko.com/coins/images/1231/large/Blox_Staking_Logo_2.png?1609117544",
		"last_updated": "2023-03-30T09:41:34.643Z",
		"low_24h": 0.330121,
		"market_cap": 243868974,
		"market_cap_change_24h": 2502642,
		"market_cap_change_percentage_24h": 1.03686,
		"market_cap_rank": 162,
		"max_supply": null,
		"name": "Blox",
		"price_change_24h": 0.00380534,
		"price_change_percentage_24h": 1.06381,
		"roi": {
			"currency": "eth",
			"percentage": 22.486837998264075,
			"times": 0.22486837998264075
		},
		"symbol": "cdt",
		"total_supply": 1000000000,
		"total_volume": 115587
	},
	{
		"ath": 4.88,
		"ath_change_percentage": -68.2067,
		"ath_date": "2022-09-11T19:47:43.631Z",
		"atl": 1.38,
		"atl_change_percentage": 12.18201,
		"atl_date": "2023-03-11T16:31:47.266Z",
		"circulating_supply": 156485525.3,
		"current_price": 1.55,
		"fully_diluted_valuation": 1376868211,
		"high_24h": 1.56,
		"id": "astrafer",
		"image": "https://assets.coingecko.com/coins/images/26246/large/ATSRA_Token.png?1657276411",
		"last_updated": "2023-03-30T09:53:41.349Z",
		"low_24h": 1.53,
		"market_cap": 242613793,
		"market_cap_change_24h": -329719.4855926335,
		"market_cap_change_percentage_24h": -0.13572,
		"market_cap_rank": 163,
		"max_supply": 888077888,
		"name": "Astrafer",
		"price_change_24h": -0.004159397535746346,
		"price_change_percentage_24h": -0.26764,
		"roi": null,
		"symbol": "astrafer",
		"total_supply": 888077888,
		"total_volume": 104599
	},
	{
		"ath": 1.32,
		"ath_change_percentage": -81.94902,
		"ath_date": "2018-04-13T09:13:22.739Z",
		"atl": 0.00913753,
		"atl_change_percentage": 2516.13608,
		"atl_date": "2016-12-12T00:00:00.000Z",
		"circulating_supply": 1000000000,
		"current_price": 0.239094,
		"fully_diluted_valuation": null,
		"high_24h": 0.243945,
		"id": "golem",
		"image": "https://assets.coingecko.com/coins/images/542/large/Golem_Submark_Positive_RGB.png?1606392013",
		"last_updated": "2023-03-30T09:53:52.185Z",
		"low_24h": 0.233734,
		"market_cap": 239169603,
		"market_cap_change_24h": 4059900,
		"market_cap_change_percentage_24h": 1.72681,
		"market_cap_rank": 165,
		"max_supply": null,
		"name": "Golem",
		"price_change_24h": 0.00393444,
		"price_change_percentage_24h": 1.6731,
		"roi": {
			"currency": "usd",
			"percentage": 2290.937889055888,
			"times": 22.90937889055888
		},
		"symbol": "glm",
		"total_supply": 1000000000,
		"total_volume": 9882193
	},
	{
		"ath": 6.48,
		"ath_change_percentage": -87.37566,
		"ath_date": "2022-01-03T14:01:45.955Z",
		"atl": 0.393069,
		"atl_change_percentage": 108.00223,
		"atl_date": "2022-11-22T11:23:02.517Z",
		"circulating_supply": 290899430.183973,
		"current_price": 0.817286,
		"fully_diluted_valuation": null,
		"high_24h": 0.827278,
		"id": "convex-crv",
		"image": "https://assets.coingecko.com/coins/images/15586/large/convex-crv.png?1621255952",
		"last_updated": "2023-03-30T09:53:20.679Z",
		"low_24h": 0.809292,
		"market_cap": 237800355,
		"market_cap_change_24h": -1263336.9202536345,
		"market_cap_change_percentage_24h": -0.52845,
		"market_cap_rank": 166,
		"max_supply": null,
		"name": "Convex CRV",
		"price_change_24h": -0.003793728539541186,
		"price_change_percentage_24h": -0.46204,
		"roi": null,
		"symbol": "cvxcrv",
		"total_supply": 290899432.352531,
		"total_volume": 178446
	},
	{
		"ath": 0.02468599,
		"ath_change_percentage": -10.80721,
		"ath_date": "2022-11-10T12:22:53.410Z",
		"atl": 0.00209672,
		"atl_change_percentage": 950.1215,
		"atl_date": "2022-11-21T00:54:17.922Z",
		"circulating_supply": 10696357927.733,
		"current_price": 0.02201229,
		"fully_diluted_valuation": null,
		"high_24h": 0.02203776,
		"id": "compound-usdt",
		"image": "https://assets.coingecko.com/coins/images/11621/large/cUSDT.png?1592113270",
		"last_updated": "2023-03-30T09:53:06.398Z",
		"low_24h": 0.01717976,
		"market_cap": 235294150,
		"market_cap_change_24h": 38369744,
		"market_cap_change_percentage_24h": 19.4845,
		"market_cap_rank": 168,
		"max_supply": null,
		"name": "cUSDT",
		"price_change_24h": 0.00477399,
		"price_change_percentage_24h": 27.69409,
		"roi": null,
		"symbol": "cusdt",
		"total_supply": 10696357927.733,
		"total_volume": 4.28
	},
	{
		"ath": 8.71,
		"ath_change_percentage": -82.086,
		"ath_date": "2021-04-21T17:13:06.858Z",
		"atl": 0.764723,
		"atl_change_percentage": 104.06448,
		"atl_date": "2022-11-14T03:16:24.229Z",
		"circulating_supply": 149318000,
		"current_price": 1.56,
		"fully_diluted_valuation": 433522132,
		"high_24h": 1.63,
		"id": "dao-maker",
		"image": "https://assets.coingecko.com/coins/images/13915/large/4.png?1612838831",
		"last_updated": "2023-03-30T09:53:57.871Z",
		"low_24h": 1.54,
		"market_cap": 233250665,
		"market_cap_change_24h": -6108711.031894237,
		"market_cap_change_percentage_24h": -2.55211,
		"market_cap_rank": 169,
		"max_supply": 277524000,
		"name": "DAO Maker",
		"price_change_24h": -0.04254718410130365,
		"price_change_percentage_24h": -2.64841,
		"roi": null,
		"symbol": "dao",
		"total_supply": 277524000,
		"total_volume": 3356637
	},
	{
		"ath": 2.61,
		"ath_change_percentage": -93.18776,
		"ath_date": "2021-10-15T08:50:14.799Z",
		"atl": 0.062214,
		"atl_change_percentage": 185.72427,
		"atl_date": "2020-11-27T03:03:31.701Z",
		"circulating_supply": 1300142684.8066669,
		"current_price": 0.17837,
		"fully_diluted_valuation": 690105223,
		"high_24h": 0.201211,
		"id": "nucypher",
		"image": "https://assets.coingecko.com/coins/images/3318/large/photo1198982838879365035.jpg?1547037916",
		"last_updated": "2023-03-30T09:53:29.868Z",
		"low_24h": 0.176997,
		"market_cap": 230925400,
		"market_cap_change_24h": -27649904.16447541,
		"market_cap_change_percentage_24h": -10.69317,
		"market_cap_rank": 171,
		"max_supply": 3885390081.74825,
		"name": "NuCypher",
		"price_change_24h": -0.02121671332128902,
		"price_change_percentage_24h": -10.63031,
		"roi": null,
		"symbol": "nu",
		"total_supply": 3885390081.74825,
		"total_volume": 30509085
	},
	{
		"ath": 22.83,
		"ath_change_percentage": -91.91468,
		"ath_date": "2021-04-15T12:04:11.270Z",
		"atl": 0.203625,
		"atl_change_percentage": 806.47832,
		"atl_date": "2019-11-25T05:49:22.765Z",
		"circulating_supply": 124138273.338711,
		"current_price": 1.86,
		"fully_diluted_valuation": 246694140,
		"high_24h": 1.94,
		"id": "band-protocol",
		"image": "https://assets.coingecko.com/coins/images/9545/large/Band_token_blue_violet_token.png?1625881431",
		"last_updated": "2023-03-30T09:53:51.714Z",
		"low_24h": 1.83,
		"market_cap": 230363485,
		"market_cap_change_24h": -2711156.973544568,
		"market_cap_change_percentage_24h": -1.16321,
		"market_cap_rank": 177,
		"max_supply": null,
		"name": "Band Protocol",
		"price_change_24h": -0.0128175815389191,
		"price_change_percentage_24h": -0.68443,
		"roi": {
			"currency": "usd",
			"percentage": 293.2197019601873,
			"times": 2.932197019601873
		},
		"symbol": "band",
		"total_supply": 132938536.331575,
		"total_volume": 27945475
	},
	{
		"ath": 4.79,
		"ath_change_percentage": -99.89904,
		"ath_date": "2021-02-16T03:53:32.207Z",
		"atl": 0.00275026,
		"atl_change_percentage": 75.8448,
		"atl_date": "2022-12-29T20:41:09.113Z",
		"circulating_supply": 47569999999.3058,
		"current_price": 0.00483875,
		"fully_diluted_valuation": 241843551,
		"high_24h": 0.00510675,
		"id": "jasmycoin",
		"image": "https://assets.coingecko.com/coins/images/13876/large/JASMY200x200.jpg?1612473259",
		"last_updated": "2023-03-30T09:53:56.411Z",
		"low_24h": 0.00473678,
		"market_cap": 230089954,
		"market_cap_change_24h": 4871943,
		"market_cap_change_percentage_24h": 2.16321,
		"market_cap_rank": 174,
		"max_supply": 50000000000,
		"name": "JasmyCoin",
		"price_change_24h": 0.00010196,
		"price_change_percentage_24h": 2.15261,
		"roi": null,
		"symbol": "jasmy",
		"total_supply": 50000000000,
		"total_volume": 98110735
	},
	{
		"ath": 1853.41,
		"ath_change_percentage": -2.96468,
		"ath_date": "2023-03-23T15:40:57.763Z",
		"atl": 1137.25,
		"atl_change_percentage": 58.14183,
		"atl_date": "2022-11-23T02:25:33.267Z",
		"circulating_supply": 127615.830630669,
		"current_price": 1798.65,
		"fully_diluted_valuation": 229536729,
		"high_24h": 1824.87,
		"id": "frax-ether",
		"image": "https://assets.coingecko.com/coins/images/28284/large/frxETH_icon.png?1679886981",
		"last_updated": "2023-03-30T09:53:35.989Z",
		"low_24h": 1785.42,
		"market_cap": 229536729,
		"market_cap_change_24h": 566449,
		"market_cap_change_percentage_24h": 0.24739,
		"market_cap_rank": 175,
		"max_supply": null,
		"name": "Frax Ether",
		"price_change_24h": -15.090284794732042,
		"price_change_percentage_24h": -0.832,
		"roi": null,
		"symbol": "frxeth",
		"total_supply": 127615.830630669,
		"total_volume": 1189416
	},
	{
		"ath": 3.61,
		"ath_change_percentage": -21.64735,
		"ath_date": "2022-06-24T02:40:08.448Z",
		"atl": 0.00064644,
		"atl_change_percentage": 437462.80141,
		"atl_date": "2021-01-10T16:54:16.852Z",
		"circulating_supply": 0,
		"current_price": 2.83,
		"fully_diluted_valuation": null,
		"high_24h": 2.91,
		"id": "escoin-token",
		"image": "https://assets.coingecko.com/coins/images/13566/large/escoin-200.png?1609833886",
		"last_updated": "2023-03-30T09:51:06.325Z",
		"low_24h": 2.82,
		"market_cap": 228752259,
		"market_cap_change_24h": 10734340,
		"market_cap_change_percentage_24h": 4.9236,
		"market_cap_rank": 176,
		"max_supply": null,
		"name": "Escoin",
		"price_change_24h": -0.04950222401443627,
		"price_change_percentage_24h": -1.71911,
		"roi": null,
		"symbol": "elg",
		"total_supply": 250000000,
		"total_volume": 3122639
	},
	{
		"ath": 25.62,
		"ath_change_percentage": -93.7039,
		"ath_date": "2018-01-13T00:00:00.000Z",
		"atl": 0.350917,
		"atl_change_percentage": 359.68236,
		"atl_date": "2020-03-13T02:30:10.072Z",
		"circulating_supply": 140245398.245133,
		"current_price": 1.62,
		"fully_diluted_valuation": 226644501,
		"high_24h": 1.81,
		"id": "omisego",
		"image": "https://assets.coingecko.com/coins/images/776/large/OMG_Network.jpg?1591167168",
		"last_updated": "2023-03-30T09:53:53.305Z",
		"low_24h": 1.6,
		"market_cap": 226644501,
		"market_cap_change_24h": -27900648.801226288,
		"market_cap_change_percentage_24h": -10.96098,
		"market_cap_rank": 178,
		"max_supply": 140245398.245133,
		"name": "OMG Network",
		"price_change_24h": -0.18775181867829827,
		"price_change_percentage_24h": -10.38646,
		"roi": null,
		"symbol": "omg",
		"total_supply": 140245398.245133,
		"total_volume": 127455579
	},
	{
		"ath": 1.31,
		"ath_change_percentage": -16.7984,
		"ath_date": "2021-09-02T00:28:44.121Z",
		"atl": 0.944541,
		"atl_change_percentage": 15.14456,
		"atl_date": "2022-09-27T16:30:27.333Z",
		"circulating_supply": 205998829.98,
		"current_price": 1.087,
		"fully_diluted_valuation": 434926363,
		"high_24h": 1.091,
		"id": "tether-eurt",
		"image": "https://assets.coingecko.com/coins/images/17385/large/Tether_full_logo_dm.png?1627537298",
		"last_updated": "2023-03-30T09:53:29.480Z",
		"low_24h": 1.075,
		"market_cap": 223985777,
		"market_cap_change_24h": 604191,
		"market_cap_change_percentage_24h": 0.27047,
		"market_cap_rank": 179,
		"max_supply": 400000050,
		"name": "Euro Tether",
		"price_change_24h": 0.00272023,
		"price_change_percentage_24h": 0.25084,
		"roi": null,
		"symbol": "eurt",
		"total_supply": 400000050,
		"total_volume": 1490690
	}
]